{
	"dialogue": [
		{
			"expression": "shy",
			"text": "Okay, okay, Jasmine sees you're a natural. I like that ina man. It gets me all excited...",
			"boxState": "normal",
			"speed": 0.05,
			"portrait": "jazzHorny"
		},
		{
			"expression": "uhoh",
			"text": "a lil too much maybe...",
			"boxState": "normal",
			"portrait": "jazzHorny",
			"speed": 0.05
		},
		{
			"expression": "talk",
			"text": "...?",
			"boxState": "normal",
			"portrait": "novaTalk",
			"speed": 0.05
		},
		{
			"expression": "mouth",
			"text": "Keep talking like that and Imma really show you what this mouth can do...",
			"boxState": "normal",
			"portrait": "jazzHorny",
			"speed": 0.05
		},
		{
			"expression": "talk",
			"text": "...",
			"boxState": "normal",
			"portrait": "novaTalk",
			"speed": 0.05
		},
		{
			"expression": "talk",
			"text": "You testing Jasmine... you don't think I got the tiddies to beat yo ass in this.",
			"boxState": "normal",
			"portrait": "jazzHorny",
			"speed": 0.05
		},
		{
			"expression": "shy",
			"text": "Imma let you lead this one, papi. Then after this...",
			"boxState": "normal",
			"speed": 0.05,
			"portrait": "jazzHorny"
		},
		{
			"speed": 0.05,
			"portrait": "jazzHorny",
			"boxState": "normal",
			"expression": "mouth",
			"text": "we going to my place..."
		}
	]
}