<?xml version="1.0" encoding="utf-8"?>
<TextureAtlas imagePath="Sign_Post_Mechanic.png">
	<!-- Created with Adobe Animate version 21.0.3.38773 -->
	<!-- http://www.adobe.com/products/animate.html -->
	<SubTexture name="Signature Stop Sign 10000" x="2.5" y="2.5" width="135" height="380.5" frameX="-324.5" frameY="-261" frameWidth="738.5" frameHeight="659"/>
	<SubTexture name="Signature Stop Sign 10001" x="2.5" y="2.5" width="135" height="380.5" frameX="-324.5" frameY="-261" frameWidth="738.5" frameHeight="659"/>
	<SubTexture name="Signature Stop Sign 10002" x="142.5" y="2.5" width="134.5" height="380.5" frameX="-328" frameY="-257" frameWidth="738.5" frameHeight="659"/>
	<SubTexture name="Signature Stop Sign 10003" x="282" y="2.5" width="134.5" height="380.5" frameX="-328" frameY="-251.5" frameWidth="738.5" frameHeight="659"/>
	<SubTexture name="Signature Stop Sign 10004" x="2.5" y="2.5" width="135" height="380.5" frameX="-327" frameY="-244" frameWidth="738.5" frameHeight="659"/>
	<SubTexture name="Signature Stop Sign 10005" x="282" y="2.5" width="134.5" height="380.5" frameX="-328" frameY="-238.5" frameWidth="738.5" frameHeight="659"/>
	<SubTexture name="Signature Stop Sign 10006" x="282" y="2.5" width="134.5" height="380.5" frameX="-328" frameY="-229.5" frameWidth="738.5" frameHeight="659"/>
	<SubTexture name="Signature Stop Sign 10007" x="282" y="2.5" width="134.5" height="380.5" frameX="-325.5" frameY="-129.5" frameWidth="738.5" frameHeight="659"/>
	<SubTexture name="Signature Stop Sign 10008" x="421.5" y="2.5" width="133" height="402.5" frameX="-342" frameY="-31" frameWidth="738.5" frameHeight="659"/>
	<SubTexture name="Signature Stop Sign 10009" x="559.5" y="2.5" width="133" height="391.5" frameX="-346" frameY="-40.5" frameWidth="738.5" frameHeight="659"/>
	<SubTexture name="Signature Stop Sign 10010" x="697.5" y="2.5" width="132.5" height="370" frameX="-348" frameY="-59.5" frameWidth="738.5" frameHeight="659"/>
	<SubTexture name="Signature Stop Sign 10011" x="835" y="2.5" width="132.5" height="376.5" frameX="-349.5" frameY="-50.5" frameWidth="738.5" frameHeight="659"/>
	<SubTexture name="Signature Stop Sign 10012" x="972.5" y="2.5" width="132.5" height="381" frameX="-345.5" frameY="-43.5" frameWidth="738.5" frameHeight="659"/>
	<SubTexture name="Signature Stop Sign 10013" x="972.5" y="2.5" width="132.5" height="381" frameX="-341" frameY="-43.5" frameWidth="738.5" frameHeight="659"/>
	<SubTexture name="Signature Stop Sign 10014" x="1110" y="2.5" width="132.5" height="381" frameX="-334.5" frameY="-42" frameWidth="738.5" frameHeight="659"/>
	<SubTexture name="Signature Stop Sign 10015" x="1247.5" y="2.5" width="133" height="381" frameX="-314.5" frameY="-37" frameWidth="738.5" frameHeight="659"/>
	<SubTexture name="Signature Stop Sign 10016" x="1110" y="2.5" width="132.5" height="381" frameX="-283.5" frameY="-32.5" frameWidth="738.5" frameHeight="659"/>
	<SubTexture name="Signature Stop Sign 10017" x="1385.5" y="2.5" width="132.5" height="381" frameX="-255.5" frameY="-24.5" frameWidth="738.5" frameHeight="659"/>
	<SubTexture name="Signature Stop Sign 10018" x="1247.5" y="2.5" width="133" height="381" frameX="-237.5" frameY="-31" frameWidth="738.5" frameHeight="659"/>
	<SubTexture name="Signature Stop Sign 10019" x="1247.5" y="2.5" width="133" height="381" frameX="-234" frameY="-34" frameWidth="738.5" frameHeight="659"/>
	<SubTexture name="Signature Stop Sign 10020" x="1523" y="2.5" width="131" height="380.5" frameX="-227" frameY="-35" frameWidth="738.5" frameHeight="659"/>
	<SubTexture name="Signature Stop Sign 10021" x="1659" y="2.5" width="131" height="381" frameX="-224" frameY="-39.5" frameWidth="738.5" frameHeight="659"/>
	<SubTexture name="Signature Stop Sign 10022" x="1795" y="2.5" width="132.5" height="381" frameX="-218.5" frameY="-42.5" frameWidth="738.5" frameHeight="659"/>
	<SubTexture name="Signature Stop Sign 10023" x="1932.5" y="2.5" width="134.5" height="381" frameX="-213" frameY="-42" frameWidth="738.5" frameHeight="659"/>
	<SubTexture name="Signature Stop Sign 10024" x="2072" y="2.5" width="133.5" height="380.5" frameX="-209" frameY="-44.5" frameWidth="738.5" frameHeight="659"/>
	<SubTexture name="Signature Stop Sign 10025" x="2210.5" y="2.5" width="136" height="380" frameX="-201" frameY="-49.5" frameWidth="738.5" frameHeight="659"/>
	<SubTexture name="Signature Stop Sign 10026" x="2351.5" y="2.5" width="136.5" height="379" frameX="-199" frameY="-50.5" frameWidth="738.5" frameHeight="659"/>
	<SubTexture name="Signature Stop Sign 10027" x="2493" y="2.5" width="136" height="379.5" frameX="-199" frameY="-47.5" frameWidth="738.5" frameHeight="659"/>
	<SubTexture name="Signature Stop Sign 10028" x="2634" y="2.5" width="172" height="370" frameX="-181.5" frameY="-45.5" frameWidth="738.5" frameHeight="659"/>
	<SubTexture name="Signature Stop Sign 10029" x="2811" y="2.5" width="172" height="370" frameX="-174.5" frameY="-44" frameWidth="738.5" frameHeight="659"/>
	<SubTexture name="Signature Stop Sign 10030" x="2988" y="2.5" width="188.5" height="364.5" frameX="-162" frameY="-40.5" frameWidth="738.5" frameHeight="659"/>
	<SubTexture name="Signature Stop Sign 10031" x="2988" y="2.5" width="188.5" height="364.5" frameX="-146" frameY="-33.5" frameWidth="738.5" frameHeight="659"/>
	<SubTexture name="Signature Stop Sign 10032" x="2988" y="2.5" width="188.5" height="364.5" frameX="-127.5" frameY="-27" frameWidth="738.5" frameHeight="659"/>
	<SubTexture name="Signature Stop Sign 10033" x="3181.5" y="2.5" width="215" height="352.5" frameX="-102.5" frameY="-24.5" frameWidth="738.5" frameHeight="659"/>
	<SubTexture name="Signature Stop Sign 10034" x="3401.5" y="2.5" width="214.5" height="352.5" frameX="-85" frameY="-18" frameWidth="738.5" frameHeight="659"/>
	<SubTexture name="Signature Stop Sign 10035" x="3181.5" y="2.5" width="215" height="352.5" frameX="-65" frameY="-13" frameWidth="738.5" frameHeight="659"/>
	<SubTexture name="Signature Stop Sign 10036" x="3621" y="2.5" width="215" height="352.5" frameX="-44" frameY="-7" frameWidth="738.5" frameHeight="659"/>
	<SubTexture name="Signature Stop Sign 10037" x="3841" y="2.5" width="220.5" height="349" frameX="-30.5" frameY="-4" frameWidth="738.5" frameHeight="659"/>
	<SubTexture name="Signature Stop Sign 10038" x="2.5" y="410" width="225" height="346.5" frameX="-10" frameY="0" frameWidth="738.5" frameHeight="659"/>
	<SubTexture name="Signature Stop Sign 10039" x="2.5" y="410" width="225" height="346.5" frameX="-5" frameY="0" frameWidth="738.5" frameHeight="659"/>
	<SubTexture name="Signature Stop Sign 10040" x="2.5" y="410" width="225" height="346.5" frameX="-2" frameY="-2" frameWidth="738.5" frameHeight="659"/>
	<SubTexture name="Signature Stop Sign 10041" x="232.5" y="410" width="225" height="346.5" frameX="-0.5" frameY="-4" frameWidth="738.5" frameHeight="659"/>
	<SubTexture name="Signature Stop Sign 10042" x="462.5" y="410" width="225" height="346.5" frameX="0" frameY="-5" frameWidth="738.5" frameHeight="659"/>
	<SubTexture name="Signature Stop Sign 10043" x="692.5" y="410" width="215.5" height="351.5" frameX="-8.5" frameY="-5" frameWidth="738.5" frameHeight="659"/>
	<SubTexture name="Signature Stop Sign 10044" x="913" y="410" width="204" height="358" frameX="-24.5" frameY="-8" frameWidth="738.5" frameHeight="659"/>
	<SubTexture name="Signature Stop Sign 10045" x="1122" y="410" width="188" height="364.5" frameX="-60.5" frameY="-18" frameWidth="738.5" frameHeight="659"/>
	<SubTexture name="Signature Stop Sign 10046" x="1315" y="410" width="186.5" height="381" frameX="-159.5" frameY="-41.5" frameWidth="738.5" frameHeight="659"/>
	<SubTexture name="Signature Stop Sign 10047" x="1506.5" y="410" width="295" height="347" frameX="-297.5" frameY="-127" frameWidth="738.5" frameHeight="659"/>
	<SubTexture name="Signature Stop Sign 10048" x="1506.5" y="410" width="295" height="347" frameX="-443" frameY="-312" frameWidth="738.5" frameHeight="659"/>
	<SubTexture name="Signature Stop Sign 10049" x="1506.5" y="410" width="295" height="347" frameX="-443" frameY="-312" frameWidth="738.5" frameHeight="659"/>
	<SubTexture name="Signature Stop Sign 10050" x="1506.5" y="410" width="295" height="347" frameX="-443" frameY="-312" frameWidth="738.5" frameHeight="659"/>
	<SubTexture name="Signature Stop Sign 20000" x="2.5" y="2.5" width="135" height="380.5" frameX="-669.5" frameY="-50.5" frameWidth="738.5" frameHeight="659"/>
	<SubTexture name="Signature Stop Sign 20001" x="1806.5" y="410" width="183" height="383" frameX="-374" frameY="-52" frameWidth="965" frameHeight="493.5"/>
	<SubTexture name="Signature Stop Sign 20002" x="1994.5" y="410" width="280.5" height="350.5" frameX="-11.5" frameY="-128" frameWidth="965" frameHeight="493.5"/>
	<SubTexture name="Signature Stop Sign 20003" x="2280" y="410" width="249.5" height="312" frameX="-11.5" frameY="-181.5" frameWidth="965" frameHeight="493.5"/>
	<SubTexture name="Signature Stop Sign 20004" x="2534.5" y="410" width="289.5" height="288.5" frameX="-14.5" frameY="-182.5" frameWidth="965" frameHeight="493.5"/>
	<SubTexture name="Signature Stop Sign 20005" x="2829" y="410" width="303.5" height="279" frameX="-2" frameY="-194.5" frameWidth="965" frameHeight="493.5"/>
	<SubTexture name="Signature Stop Sign 20006" x="2829" y="410" width="303.5" height="279" frameX="-1" frameY="-198" frameWidth="965" frameHeight="493.5"/>
	<SubTexture name="Signature Stop Sign 20007" x="3137.5" y="410" width="303.5" height="278.5" frameX="-0.5" frameY="-201" frameWidth="965" frameHeight="493.5"/>
	<SubTexture name="Signature Stop Sign 20008" x="2829" y="410" width="303.5" height="279" frameX="0" frameY="-202.5" frameWidth="965" frameHeight="493.5"/>
	<SubTexture name="Signature Stop Sign 20009" x="2829" y="410" width="303.5" height="279" frameX="0" frameY="-202.5" frameWidth="965" frameHeight="493.5"/>
	<SubTexture name="Signature Stop Sign 20010" x="2829" y="410" width="303.5" height="279" frameX="-4.5" frameY="-193.5" frameWidth="965" frameHeight="493.5"/>
	<SubTexture name="Signature Stop Sign 20011" x="3446" y="410" width="262.5" height="360.5" frameX="-201" frameY="-24" frameWidth="965" frameHeight="493.5"/>
	<SubTexture name="Signature Stop Sign 20012" x="3713.5" y="410" width="89.5" height="380.5" frameX="-382.5" frameY="0" frameWidth="965" frameHeight="493.5"/>
	<SubTexture name="Signature Stop Sign 20013" x="3808" y="410" width="118" height="381" frameX="-390" frameY="-5.5" frameWidth="965" frameHeight="493.5"/>
	<SubTexture name="Signature Stop Sign 20014" x="2.5" y="798" width="290.5" height="344" frameX="-50.5" frameY="-97" frameWidth="965" frameHeight="493.5"/>
	<SubTexture name="Signature Stop Sign 20015" x="298" y="798" width="260.5" height="303" frameX="-82.5" frameY="-133.5" frameWidth="965" frameHeight="493.5"/>
	<SubTexture name="Signature Stop Sign 20016" x="563.5" y="798" width="287.5" height="290.5" frameX="-56" frameY="-154.5" frameWidth="965" frameHeight="493.5"/>
	<SubTexture name="Signature Stop Sign 20017" x="3446" y="410" width="262.5" height="360.5" frameX="-201" frameY="-24" frameWidth="965" frameHeight="493.5"/>
	<SubTexture name="Signature Stop Sign 20018" x="3713.5" y="410" width="89.5" height="380.5" frameX="-382.5" frameY="0" frameWidth="965" frameHeight="493.5"/>
	<SubTexture name="Signature Stop Sign 20019" x="3808" y="410" width="118" height="381" frameX="-390" frameY="-5.5" frameWidth="965" frameHeight="493.5"/>
	<SubTexture name="Signature Stop Sign 20020" x="2.5" y="798" width="290.5" height="344" frameX="-50.5" frameY="-97" frameWidth="965" frameHeight="493.5"/>
	<SubTexture name="Signature Stop Sign 20021" x="298" y="798" width="260.5" height="303" frameX="-82.5" frameY="-133.5" frameWidth="965" frameHeight="493.5"/>
	<SubTexture name="Signature Stop Sign 20022" x="563.5" y="798" width="287.5" height="290.5" frameX="-56" frameY="-154.5" frameWidth="965" frameHeight="493.5"/>
	<SubTexture name="Signature Stop Sign 20023" x="3446" y="410" width="262.5" height="360.5" frameX="-201" frameY="-24" frameWidth="965" frameHeight="493.5"/>
	<SubTexture name="Signature Stop Sign 20024" x="3713.5" y="410" width="89.5" height="380.5" frameX="-382.5" frameY="0" frameWidth="965" frameHeight="493.5"/>
	<SubTexture name="Signature Stop Sign 20025" x="3808" y="410" width="118" height="381" frameX="-390" frameY="-5.5" frameWidth="965" frameHeight="493.5"/>
	<SubTexture name="Signature Stop Sign 20026" x="2.5" y="798" width="290.5" height="344" frameX="-50.5" frameY="-97" frameWidth="965" frameHeight="493.5"/>
	<SubTexture name="Signature Stop Sign 20027" x="298" y="798" width="260.5" height="303" frameX="-82.5" frameY="-133.5" frameWidth="965" frameHeight="493.5"/>
	<SubTexture name="Signature Stop Sign 20028" x="563.5" y="798" width="287.5" height="290.5" frameX="-56" frameY="-154.5" frameWidth="965" frameHeight="493.5"/>
	<SubTexture name="Signature Stop Sign 20029" x="3446" y="410" width="262.5" height="360.5" frameX="-201" frameY="-24" frameWidth="965" frameHeight="493.5"/>
	<SubTexture name="Signature Stop Sign 20030" x="3713.5" y="410" width="89.5" height="380.5" frameX="-382.5" frameY="0" frameWidth="965" frameHeight="493.5"/>
	<SubTexture name="Signature Stop Sign 20031" x="3808" y="410" width="118" height="381" frameX="-390" frameY="-5.5" frameWidth="965" frameHeight="493.5"/>
	<SubTexture name="Signature Stop Sign 20032" x="2.5" y="798" width="290.5" height="344" frameX="-50.5" frameY="-97" frameWidth="965" frameHeight="493.5"/>
	<SubTexture name="Signature Stop Sign 20033" x="298" y="798" width="260.5" height="303" frameX="-82.5" frameY="-133.5" frameWidth="965" frameHeight="493.5"/>
	<SubTexture name="Signature Stop Sign 20034" x="563.5" y="798" width="287.5" height="290.5" frameX="-56" frameY="-154.5" frameWidth="965" frameHeight="493.5"/>
	<SubTexture name="Signature Stop Sign 20035" x="3446" y="410" width="262.5" height="360.5" frameX="-201" frameY="-24" frameWidth="965" frameHeight="493.5"/>
	<SubTexture name="Signature Stop Sign 20036" x="3713.5" y="410" width="89.5" height="380.5" frameX="-382.5" frameY="0" frameWidth="965" frameHeight="493.5"/>
	<SubTexture name="Signature Stop Sign 20037" x="3808" y="410" width="118" height="381" frameX="-390" frameY="-5.5" frameWidth="965" frameHeight="493.5"/>
	<SubTexture name="Signature Stop Sign 20038" x="2.5" y="798" width="290.5" height="344" frameX="-50.5" frameY="-97" frameWidth="965" frameHeight="493.5"/>
	<SubTexture name="Signature Stop Sign 20039" x="298" y="798" width="260.5" height="303" frameX="-82.5" frameY="-133.5" frameWidth="965" frameHeight="493.5"/>
	<SubTexture name="Signature Stop Sign 20040" x="563.5" y="798" width="287.5" height="290.5" frameX="-56" frameY="-154.5" frameWidth="965" frameHeight="493.5"/>
	<SubTexture name="Signature Stop Sign 20041" x="3446" y="410" width="262.5" height="360.5" frameX="-201" frameY="-24" frameWidth="965" frameHeight="493.5"/>
	<SubTexture name="Signature Stop Sign 20042" x="3713.5" y="410" width="89.5" height="380.5" frameX="-382.5" frameY="0" frameWidth="965" frameHeight="493.5"/>
	<SubTexture name="Signature Stop Sign 20043" x="3808" y="410" width="118" height="381" frameX="-390" frameY="-5.5" frameWidth="965" frameHeight="493.5"/>
	<SubTexture name="Signature Stop Sign 20044" x="2.5" y="798" width="290.5" height="344" frameX="-50.5" frameY="-97" frameWidth="965" frameHeight="493.5"/>
	<SubTexture name="Signature Stop Sign 20045" x="298" y="798" width="260.5" height="303" frameX="-82.5" frameY="-133.5" frameWidth="965" frameHeight="493.5"/>
	<SubTexture name="Signature Stop Sign 20046" x="563.5" y="798" width="287.5" height="290.5" frameX="-56" frameY="-154.5" frameWidth="965" frameHeight="493.5"/>
	<SubTexture name="Signature Stop Sign 20047" x="3446" y="410" width="262.5" height="360.5" frameX="-201" frameY="-24" frameWidth="965" frameHeight="493.5"/>
	<SubTexture name="Signature Stop Sign 20048" x="3713.5" y="410" width="89.5" height="380.5" frameX="-382.5" frameY="0" frameWidth="965" frameHeight="493.5"/>
	<SubTexture name="Signature Stop Sign 20049" x="3808" y="410" width="118" height="381" frameX="-390" frameY="-5.5" frameWidth="965" frameHeight="493.5"/>
	<SubTexture name="Signature Stop Sign 20050" x="2.5" y="798" width="290.5" height="344" frameX="-50.5" frameY="-97" frameWidth="965" frameHeight="493.5"/>
	<SubTexture name="Signature Stop Sign 20051" x="298" y="798" width="260.5" height="303" frameX="-82.5" frameY="-133.5" frameWidth="965" frameHeight="493.5"/>
	<SubTexture name="Signature Stop Sign 20052" x="563.5" y="798" width="287.5" height="290.5" frameX="-56" frameY="-154.5" frameWidth="965" frameHeight="493.5"/>
	<SubTexture name="Signature Stop Sign 20053" x="3446" y="410" width="262.5" height="360.5" frameX="-201" frameY="-24" frameWidth="965" frameHeight="493.5"/>
	<SubTexture name="Signature Stop Sign 20054" x="3713.5" y="410" width="89.5" height="380.5" frameX="-382.5" frameY="0" frameWidth="965" frameHeight="493.5"/>
	<SubTexture name="Signature Stop Sign 20055" x="3808" y="410" width="118" height="381" frameX="-390" frameY="-5.5" frameWidth="965" frameHeight="493.5"/>
	<SubTexture name="Signature Stop Sign 20056" x="2.5" y="798" width="290.5" height="344" frameX="-50.5" frameY="-97" frameWidth="965" frameHeight="493.5"/>
	<SubTexture name="Signature Stop Sign 20057" x="298" y="798" width="260.5" height="303" frameX="-82.5" frameY="-133.5" frameWidth="965" frameHeight="493.5"/>
	<SubTexture name="Signature Stop Sign 20058" x="563.5" y="798" width="287.5" height="290.5" frameX="-56" frameY="-154.5" frameWidth="965" frameHeight="493.5"/>
	<SubTexture name="Signature Stop Sign 20059" x="3446" y="410" width="262.5" height="360.5" frameX="-201" frameY="-24" frameWidth="965" frameHeight="493.5"/>
	<SubTexture name="Signature Stop Sign 20060" x="3713.5" y="410" width="89.5" height="380.5" frameX="-382.5" frameY="0" frameWidth="965" frameHeight="493.5"/>
	<SubTexture name="Signature Stop Sign 20061" x="3808" y="410" width="118" height="381" frameX="-390" frameY="-5.5" frameWidth="965" frameHeight="493.5"/>
	<SubTexture name="Signature Stop Sign 20062" x="2.5" y="798" width="290.5" height="344" frameX="-50.5" frameY="-97" frameWidth="965" frameHeight="493.5"/>
	<SubTexture name="Signature Stop Sign 20063" x="298" y="798" width="260.5" height="303" frameX="-82.5" frameY="-133.5" frameWidth="965" frameHeight="493.5"/>
	<SubTexture name="Signature Stop Sign 20064" x="563.5" y="798" width="287.5" height="290.5" frameX="-56" frameY="-154.5" frameWidth="965" frameHeight="493.5"/>
	<SubTexture name="Signature Stop Sign 20065" x="856" y="798" width="313" height="267.5" frameX="-41" frameY="-170.5" frameWidth="965" frameHeight="493.5"/>
	<SubTexture name="Signature Stop Sign 20066" x="1174" y="798" width="321.5" height="256" frameX="-36.5" frameY="-180.5" frameWidth="965" frameHeight="493.5"/>
	<SubTexture name="Signature Stop Sign 20067" x="1500.5" y="798" width="328.5" height="247" frameX="-35" frameY="-189.5" frameWidth="965" frameHeight="493.5"/>
	<SubTexture name="Signature Stop Sign 20068" x="1834" y="798" width="334" height="240.5" frameX="-33.5" frameY="-195.5" frameWidth="965" frameHeight="493.5"/>
	<SubTexture name="Signature Stop Sign 20069" x="1834" y="798" width="334" height="240.5" frameX="-33.5" frameY="-195.5" frameWidth="965" frameHeight="493.5"/>
	<SubTexture name="Signature Stop Sign 20070" x="2173" y="798" width="249.5" height="366.5" frameX="-212.5" frameY="-45.5" frameWidth="965" frameHeight="493.5"/>
	<SubTexture name="Signature Stop Sign 20071" x="2427.5" y="798" width="257.5" height="334.5" frameX="-484.5" frameY="-74.5" frameWidth="965" frameHeight="493.5"/>
	<SubTexture name="Signature Stop Sign 20072" x="2690" y="798" width="258.5" height="334.5" frameX="-704.5" frameY="-110.5" frameWidth="965" frameHeight="493.5"/>
	<SubTexture name="Signature Stop Sign 20073" x="2953.5" y="798" width="258" height="334.5" frameX="-707" frameY="-108.5" frameWidth="965" frameHeight="493.5"/>
	<SubTexture name="Signature Stop Sign 30000" x="3216.5" y="798" width="135" height="380.5" frameX="-57" frameY="-355" frameWidth="211.5" frameHeight="796.5"/>
	<SubTexture name="Signature Stop Sign 30001" x="3356.5" y="798" width="135.5" height="380.5" frameX="-17" frameY="-100" frameWidth="211.5" frameHeight="796.5"/>
	<SubTexture name="Signature Stop Sign 30002" x="3356.5" y="798" width="135.5" height="380.5" frameX="-2" frameY="-2" frameWidth="211.5" frameHeight="796.5"/>
	<SubTexture name="Signature Stop Sign 30003" x="3497" y="798" width="135.5" height="380" frameX="-0.5" frameY="-11.5" frameWidth="211.5" frameHeight="796.5"/>
	<SubTexture name="Signature Stop Sign 30004" x="3497" y="798" width="135.5" height="380" frameX="-1.5" frameY="-22.5" frameWidth="211.5" frameHeight="796.5"/>
	<SubTexture name="Signature Stop Sign 30005" x="3637.5" y="798" width="135.5" height="380" frameX="-1.5" frameY="-28" frameWidth="211.5" frameHeight="796.5"/>
	<SubTexture name="Signature Stop Sign 30006" x="3497" y="798" width="135.5" height="380" frameX="-1" frameY="-31" frameWidth="211.5" frameHeight="796.5"/>
	<SubTexture name="Signature Stop Sign 30007" x="3778" y="798" width="134.5" height="380.5" frameX="-11.5" frameY="-79" frameWidth="211.5" frameHeight="796.5"/>
	<SubTexture name="Signature Stop Sign 30008" x="3917.5" y="798" width="135" height="380.5" frameX="-23.5" frameY="-188" frameWidth="211.5" frameHeight="796.5"/>
	<SubTexture name="Signature Stop Sign 30009" x="3778" y="798" width="134.5" height="380.5" frameX="-26" frameY="-178" frameWidth="211.5" frameHeight="796.5"/>
	<SubTexture name="Signature Stop Sign 30010" x="3917.5" y="798" width="135" height="380.5" frameX="-26.5" frameY="-170" frameWidth="211.5" frameHeight="796.5"/>
	<SubTexture name="Signature Stop Sign 30011" x="3917.5" y="798" width="135" height="380.5" frameX="-24.5" frameY="-166.5" frameWidth="211.5" frameHeight="796.5"/>
	<SubTexture name="Signature Stop Sign 30012" x="3778" y="798" width="134.5" height="380.5" frameX="-25.5" frameY="-165" frameWidth="211.5" frameHeight="796.5"/>
	<SubTexture name="Signature Stop Sign 30013" x="3778" y="798" width="134.5" height="380.5" frameX="-25.5" frameY="-165" frameWidth="211.5" frameHeight="796.5"/>
	<SubTexture name="Signature Stop Sign 30014" x="3356.5" y="798" width="135.5" height="380.5" frameX="-2" frameY="-2" frameWidth="211.5" frameHeight="796.5"/>
	<SubTexture name="Signature Stop Sign 30015" x="3497" y="798" width="135.5" height="380" frameX="-0.5" frameY="-11.5" frameWidth="211.5" frameHeight="796.5"/>
	<SubTexture name="Signature Stop Sign 30016" x="3497" y="798" width="135.5" height="380" frameX="-1.5" frameY="-22.5" frameWidth="211.5" frameHeight="796.5"/>
	<SubTexture name="Signature Stop Sign 30017" x="3637.5" y="798" width="135.5" height="380" frameX="-1.5" frameY="-28" frameWidth="211.5" frameHeight="796.5"/>
	<SubTexture name="Signature Stop Sign 30018" x="3497" y="798" width="135.5" height="380" frameX="-1" frameY="-31" frameWidth="211.5" frameHeight="796.5"/>
	<SubTexture name="Signature Stop Sign 30019" x="3778" y="798" width="134.5" height="380.5" frameX="-11.5" frameY="-79" frameWidth="211.5" frameHeight="796.5"/>
	<SubTexture name="Signature Stop Sign 30020" x="3917.5" y="798" width="135" height="380.5" frameX="-23.5" frameY="-188" frameWidth="211.5" frameHeight="796.5"/>
	<SubTexture name="Signature Stop Sign 30021" x="3778" y="798" width="134.5" height="380.5" frameX="-26" frameY="-178" frameWidth="211.5" frameHeight="796.5"/>
	<SubTexture name="Signature Stop Sign 30022" x="3917.5" y="798" width="135" height="380.5" frameX="-26.5" frameY="-170" frameWidth="211.5" frameHeight="796.5"/>
	<SubTexture name="Signature Stop Sign 30023" x="3917.5" y="798" width="135" height="380.5" frameX="-24.5" frameY="-166.5" frameWidth="211.5" frameHeight="796.5"/>
	<SubTexture name="Signature Stop Sign 30024" x="3778" y="798" width="134.5" height="380.5" frameX="-25.5" frameY="-165" frameWidth="211.5" frameHeight="796.5"/>
	<SubTexture name="Signature Stop Sign 30025" x="3778" y="798" width="134.5" height="380.5" frameX="-25.5" frameY="-165" frameWidth="211.5" frameHeight="796.5"/>
	<SubTexture name="Signature Stop Sign 30026" x="3356.5" y="798" width="135.5" height="380.5" frameX="-2" frameY="-2" frameWidth="211.5" frameHeight="796.5"/>
	<SubTexture name="Signature Stop Sign 30027" x="3497" y="798" width="135.5" height="380" frameX="-0.5" frameY="-11.5" frameWidth="211.5" frameHeight="796.5"/>
	<SubTexture name="Signature Stop Sign 30028" x="3497" y="798" width="135.5" height="380" frameX="-1.5" frameY="-22.5" frameWidth="211.5" frameHeight="796.5"/>
	<SubTexture name="Signature Stop Sign 30029" x="3637.5" y="798" width="135.5" height="380" frameX="-1.5" frameY="-28" frameWidth="211.5" frameHeight="796.5"/>
	<SubTexture name="Signature Stop Sign 30030" x="3497" y="798" width="135.5" height="380" frameX="-1" frameY="-31" frameWidth="211.5" frameHeight="796.5"/>
	<SubTexture name="Signature Stop Sign 30031" x="3778" y="798" width="134.5" height="380.5" frameX="-11.5" frameY="-79" frameWidth="211.5" frameHeight="796.5"/>
	<SubTexture name="Signature Stop Sign 30032" x="3917.5" y="798" width="135" height="380.5" frameX="-23.5" frameY="-188" frameWidth="211.5" frameHeight="796.5"/>
	<SubTexture name="Signature Stop Sign 30033" x="3778" y="798" width="134.5" height="380.5" frameX="-26" frameY="-178" frameWidth="211.5" frameHeight="796.5"/>
	<SubTexture name="Signature Stop Sign 30034" x="3917.5" y="798" width="135" height="380.5" frameX="-26.5" frameY="-170" frameWidth="211.5" frameHeight="796.5"/>
	<SubTexture name="Signature Stop Sign 30035" x="3917.5" y="798" width="135" height="380.5" frameX="-24.5" frameY="-166.5" frameWidth="211.5" frameHeight="796.5"/>
	<SubTexture name="Signature Stop Sign 30036" x="3778" y="798" width="134.5" height="380.5" frameX="-25.5" frameY="-165" frameWidth="211.5" frameHeight="796.5"/>
	<SubTexture name="Signature Stop Sign 30037" x="3778" y="798" width="134.5" height="380.5" frameX="-25.5" frameY="-165" frameWidth="211.5" frameHeight="796.5"/>
	<SubTexture name="Signature Stop Sign 30038" x="3356.5" y="798" width="135.5" height="380.5" frameX="-2" frameY="-2" frameWidth="211.5" frameHeight="796.5"/>
	<SubTexture name="Signature Stop Sign 30039" x="3497" y="798" width="135.5" height="380" frameX="-0.5" frameY="-11.5" frameWidth="211.5" frameHeight="796.5"/>
	<SubTexture name="Signature Stop Sign 30040" x="3497" y="798" width="135.5" height="380" frameX="-1.5" frameY="-22.5" frameWidth="211.5" frameHeight="796.5"/>
	<SubTexture name="Signature Stop Sign 30041" x="3637.5" y="798" width="135.5" height="380" frameX="-1.5" frameY="-28" frameWidth="211.5" frameHeight="796.5"/>
	<SubTexture name="Signature Stop Sign 30042" x="3497" y="798" width="135.5" height="380" frameX="-1" frameY="-31" frameWidth="211.5" frameHeight="796.5"/>
	<SubTexture name="Signature Stop Sign 30043" x="3778" y="798" width="134.5" height="380.5" frameX="-11.5" frameY="-79" frameWidth="211.5" frameHeight="796.5"/>
	<SubTexture name="Signature Stop Sign 30044" x="3917.5" y="798" width="135" height="380.5" frameX="-23.5" frameY="-188" frameWidth="211.5" frameHeight="796.5"/>
	<SubTexture name="Signature Stop Sign 30045" x="3778" y="798" width="134.5" height="380.5" frameX="-26" frameY="-178" frameWidth="211.5" frameHeight="796.5"/>
	<SubTexture name="Signature Stop Sign 30046" x="3917.5" y="798" width="135" height="380.5" frameX="-26.5" frameY="-170" frameWidth="211.5" frameHeight="796.5"/>
	<SubTexture name="Signature Stop Sign 30047" x="3917.5" y="798" width="135" height="380.5" frameX="-24.5" frameY="-166.5" frameWidth="211.5" frameHeight="796.5"/>
	<SubTexture name="Signature Stop Sign 30048" x="3778" y="798" width="134.5" height="380.5" frameX="-25.5" frameY="-165" frameWidth="211.5" frameHeight="796.5"/>
	<SubTexture name="Signature Stop Sign 30049" x="3778" y="798" width="134.5" height="380.5" frameX="-25.5" frameY="-165" frameWidth="211.5" frameHeight="796.5"/>
	<SubTexture name="Signature Stop Sign 30050" x="3356.5" y="798" width="135.5" height="380.5" frameX="-2" frameY="-2" frameWidth="211.5" frameHeight="796.5"/>
	<SubTexture name="Signature Stop Sign 30051" x="3497" y="798" width="135.5" height="380" frameX="-0.5" frameY="-11.5" frameWidth="211.5" frameHeight="796.5"/>
	<SubTexture name="Signature Stop Sign 30052" x="3497" y="798" width="135.5" height="380" frameX="-1.5" frameY="-22.5" frameWidth="211.5" frameHeight="796.5"/>
	<SubTexture name="Signature Stop Sign 30053" x="3637.5" y="798" width="135.5" height="380" frameX="-1.5" frameY="-28" frameWidth="211.5" frameHeight="796.5"/>
	<SubTexture name="Signature Stop Sign 30054" x="3497" y="798" width="135.5" height="380" frameX="-1" frameY="-31" frameWidth="211.5" frameHeight="796.5"/>
	<SubTexture name="Signature Stop Sign 30055" x="3778" y="798" width="134.5" height="380.5" frameX="-11.5" frameY="-79" frameWidth="211.5" frameHeight="796.5"/>
	<SubTexture name="Signature Stop Sign 30056" x="3917.5" y="798" width="135" height="380.5" frameX="-23.5" frameY="-188" frameWidth="211.5" frameHeight="796.5"/>
	<SubTexture name="Signature Stop Sign 30057" x="3778" y="798" width="134.5" height="380.5" frameX="-26" frameY="-178" frameWidth="211.5" frameHeight="796.5"/>
	<SubTexture name="Signature Stop Sign 30058" x="3917.5" y="798" width="135" height="380.5" frameX="-26.5" frameY="-170" frameWidth="211.5" frameHeight="796.5"/>
	<SubTexture name="Signature Stop Sign 30059" x="3917.5" y="798" width="135" height="380.5" frameX="-24.5" frameY="-166.5" frameWidth="211.5" frameHeight="796.5"/>
	<SubTexture name="Signature Stop Sign 30060" x="3778" y="798" width="134.5" height="380.5" frameX="-25.5" frameY="-165" frameWidth="211.5" frameHeight="796.5"/>
	<SubTexture name="Signature Stop Sign 30061" x="3778" y="798" width="134.5" height="380.5" frameX="-25.5" frameY="-165" frameWidth="211.5" frameHeight="796.5"/>
	<SubTexture name="Signature Stop Sign 30062" x="3356.5" y="798" width="135.5" height="380.5" frameX="-2" frameY="-2" frameWidth="211.5" frameHeight="796.5"/>
	<SubTexture name="Signature Stop Sign 30063" x="3497" y="798" width="135.5" height="380" frameX="-0.5" frameY="-11.5" frameWidth="211.5" frameHeight="796.5"/>
	<SubTexture name="Signature Stop Sign 30064" x="3497" y="798" width="135.5" height="380" frameX="-1.5" frameY="-22.5" frameWidth="211.5" frameHeight="796.5"/>
	<SubTexture name="Signature Stop Sign 30065" x="3637.5" y="798" width="135.5" height="380" frameX="-1.5" frameY="-28" frameWidth="211.5" frameHeight="796.5"/>
	<SubTexture name="Signature Stop Sign 30066" x="3497" y="798" width="135.5" height="380" frameX="-1" frameY="-31" frameWidth="211.5" frameHeight="796.5"/>
	<SubTexture name="Signature Stop Sign 30067" x="3497" y="798" width="135.5" height="380" frameX="-1" frameY="-21.5" frameWidth="211.5" frameHeight="796.5"/>
	<SubTexture name="Signature Stop Sign 30068" x="3497" y="798" width="135.5" height="380" frameX="0" frameY="-8.5" frameWidth="211.5" frameHeight="796.5"/>
	<SubTexture name="Signature Stop Sign 30069" x="3497" y="798" width="135.5" height="380" frameX="-0.5" frameY="-4" frameWidth="211.5" frameHeight="796.5"/>
	<SubTexture name="Signature Stop Sign 30070" x="3637.5" y="798" width="135.5" height="380" frameX="-0.5" frameY="-1.5" frameWidth="211.5" frameHeight="796.5"/>
	<SubTexture name="Signature Stop Sign 30071" x="3637.5" y="798" width="135.5" height="380" frameX="-1" frameY="0" frameWidth="211.5" frameHeight="796.5"/>
	<SubTexture name="Signature Stop Sign 30072" x="3778" y="798" width="134.5" height="380.5" frameX="-11.5" frameY="-79" frameWidth="211.5" frameHeight="796.5"/>
	<SubTexture name="Signature Stop Sign 30073" x="2.5" y="1183.5" width="135" height="380.5" frameX="-35.5" frameY="-238.5" frameWidth="211.5" frameHeight="796.5"/>
	<SubTexture name="Signature Stop Sign 30074" x="142.5" y="1183.5" width="135.5" height="380.5" frameX="-76" frameY="-416" frameWidth="211.5" frameHeight="796.5"/>
	<SubTexture name="Signature Stop Sign 30075" x="142.5" y="1183.5" width="135.5" height="380.5" frameX="-76" frameY="-416" frameWidth="211.5" frameHeight="796.5"/>
	<SubTexture name="Signature Stop Sign 30076" x="142.5" y="1183.5" width="135.5" height="380.5" frameX="-76" frameY="-416" frameWidth="211.5" frameHeight="796.5"/>
	<SubTexture name="Signature Stop Sign 40000" x="283" y="1183.5" width="131" height="518.5" frameX="-435" frameY="-606.5" frameWidth="625" frameHeight="1125"/>
	<SubTexture name="Signature Stop Sign 40001" x="419" y="1183.5" width="223.5" height="518" frameX="-396" frameY="-285" frameWidth="625" frameHeight="1125"/>
	<SubTexture name="Signature Stop Sign 40002" x="647.5" y="1183.5" width="226.5" height="518" frameX="-398.5" frameY="-101" frameWidth="625" frameHeight="1125"/>
	<SubTexture name="Signature Stop Sign 40003" x="879" y="1183.5" width="132" height="717" frameX="-445" frameY="0" frameWidth="625" frameHeight="1125"/>
	<SubTexture name="Signature Stop Sign 40004" x="1016" y="1183.5" width="132" height="694" frameX="-445" frameY="-28" frameWidth="625" frameHeight="1125"/>
	<SubTexture name="Signature Stop Sign 40005" x="1153" y="1183.5" width="131.5" height="518" frameX="-442.5" frameY="-59.5" frameWidth="625" frameHeight="1125"/>
	<SubTexture name="Signature Stop Sign 40006" x="1153" y="1183.5" width="131.5" height="518" frameX="-443" frameY="-68.5" frameWidth="625" frameHeight="1125"/>
	<SubTexture name="Signature Stop Sign 40007" x="1153" y="1183.5" width="131.5" height="518" frameX="-443" frameY="-72.5" frameWidth="625" frameHeight="1125"/>
	<SubTexture name="Signature Stop Sign 40008" x="1153" y="1183.5" width="131.5" height="518" frameX="-443" frameY="-70.5" frameWidth="625" frameHeight="1125"/>
	<SubTexture name="Signature Stop Sign 40009" x="1153" y="1183.5" width="131.5" height="518" frameX="-442.5" frameY="-69.5" frameWidth="625" frameHeight="1125"/>
	<SubTexture name="Signature Stop Sign 40010" x="1153" y="1183.5" width="131.5" height="518" frameX="-442.5" frameY="-69.5" frameWidth="625" frameHeight="1125"/>
	<SubTexture name="Signature Stop Sign 40011" x="1153" y="1183.5" width="131.5" height="518" frameX="-442.5" frameY="-69.5" frameWidth="625" frameHeight="1125"/>
	<SubTexture name="Signature Stop Sign 40012" x="1153" y="1183.5" width="131.5" height="518" frameX="-442.5" frameY="-69.5" frameWidth="625" frameHeight="1125"/>
	<SubTexture name="Signature Stop Sign 40013" x="1153" y="1183.5" width="131.5" height="518" frameX="-442.5" frameY="-69.5" frameWidth="625" frameHeight="1125"/>
	<SubTexture name="Signature Stop Sign 40014" x="1153" y="1183.5" width="131.5" height="518" frameX="-442.5" frameY="-69.5" frameWidth="625" frameHeight="1125"/>
	<SubTexture name="Signature Stop Sign 40015" x="1153" y="1183.5" width="131.5" height="518" frameX="-442.5" frameY="-69.5" frameWidth="625" frameHeight="1125"/>
	<SubTexture name="Signature Stop Sign 40016" x="1153" y="1183.5" width="131.5" height="518" frameX="-442.5" frameY="-69.5" frameWidth="625" frameHeight="1125"/>
	<SubTexture name="Signature Stop Sign 40017" x="1153" y="1183.5" width="131.5" height="518" frameX="-442.5" frameY="-69.5" frameWidth="625" frameHeight="1125"/>
	<SubTexture name="Signature Stop Sign 40018" x="1153" y="1183.5" width="131.5" height="518" frameX="-442.5" frameY="-69.5" frameWidth="625" frameHeight="1125"/>
	<SubTexture name="Signature Stop Sign 40019" x="1153" y="1183.5" width="131.5" height="518" frameX="-442.5" frameY="-69.5" frameWidth="625" frameHeight="1125"/>
	<SubTexture name="Signature Stop Sign 40020" x="1153" y="1183.5" width="131.5" height="518" frameX="-442.5" frameY="-69.5" frameWidth="625" frameHeight="1125"/>
	<SubTexture name="Signature Stop Sign 40021" x="1153" y="1183.5" width="131.5" height="518" frameX="-442.5" frameY="-69.5" frameWidth="625" frameHeight="1125"/>
	<SubTexture name="Signature Stop Sign 40022" x="1153" y="1183.5" width="131.5" height="518" frameX="-442.5" frameY="-69.5" frameWidth="625" frameHeight="1125"/>
	<SubTexture name="Signature Stop Sign 40023" x="1153" y="1183.5" width="131.5" height="518" frameX="-442.5" frameY="-69.5" frameWidth="625" frameHeight="1125"/>
	<SubTexture name="Signature Stop Sign 40024" x="1153" y="1183.5" width="131.5" height="518" frameX="-442.5" frameY="-69.5" frameWidth="625" frameHeight="1125"/>
	<SubTexture name="Signature Stop Sign 40025" x="1153" y="1183.5" width="131.5" height="518" frameX="-442.5" frameY="-69.5" frameWidth="625" frameHeight="1125"/>
	<SubTexture name="Signature Stop Sign 40026" x="1153" y="1183.5" width="131.5" height="518" frameX="-442.5" frameY="-69.5" frameWidth="625" frameHeight="1125"/>
	<SubTexture name="Signature Stop Sign 40027" x="1153" y="1183.5" width="131.5" height="518" frameX="-442.5" frameY="-69.5" frameWidth="625" frameHeight="1125"/>
	<SubTexture name="Signature Stop Sign 40028" x="1153" y="1183.5" width="131.5" height="518" frameX="-442.5" frameY="-69.5" frameWidth="625" frameHeight="1125"/>
	<SubTexture name="Signature Stop Sign 40029" x="1153" y="1183.5" width="131.5" height="518" frameX="-442.5" frameY="-69.5" frameWidth="625" frameHeight="1125"/>
	<SubTexture name="Signature Stop Sign 40030" x="1153" y="1183.5" width="131.5" height="518" frameX="-442.5" frameY="-69.5" frameWidth="625" frameHeight="1125"/>
	<SubTexture name="Signature Stop Sign 40031" x="1153" y="1183.5" width="131.5" height="518" frameX="-442.5" frameY="-69.5" frameWidth="625" frameHeight="1125"/>
	<SubTexture name="Signature Stop Sign 40032" x="1153" y="1183.5" width="131.5" height="518" frameX="-442.5" frameY="-69.5" frameWidth="625" frameHeight="1125"/>
	<SubTexture name="Signature Stop Sign 40033" x="1153" y="1183.5" width="131.5" height="518" frameX="-442.5" frameY="-69.5" frameWidth="625" frameHeight="1125"/>
	<SubTexture name="Signature Stop Sign 40034" x="1153" y="1183.5" width="131.5" height="518" frameX="-442.5" frameY="-69.5" frameWidth="625" frameHeight="1125"/>
	<SubTexture name="Signature Stop Sign 40035" x="1153" y="1183.5" width="131.5" height="518" frameX="-442.5" frameY="-69.5" frameWidth="625" frameHeight="1125"/>
	<SubTexture name="Signature Stop Sign 40036" x="1153" y="1183.5" width="131.5" height="518" frameX="-442.5" frameY="-69.5" frameWidth="625" frameHeight="1125"/>
	<SubTexture name="Signature Stop Sign 40037" x="1153" y="1183.5" width="131.5" height="518" frameX="-442.5" frameY="-69.5" frameWidth="625" frameHeight="1125"/>
	<SubTexture name="Signature Stop Sign 40038" x="1153" y="1183.5" width="131.5" height="518" frameX="-442.5" frameY="-69.5" frameWidth="625" frameHeight="1125"/>
	<SubTexture name="Signature Stop Sign 40039" x="1153" y="1183.5" width="131.5" height="518" frameX="-442.5" frameY="-69.5" frameWidth="625" frameHeight="1125"/>
	<SubTexture name="Signature Stop Sign 40040" x="1153" y="1183.5" width="131.5" height="518" frameX="-442.5" frameY="-69.5" frameWidth="625" frameHeight="1125"/>
	<SubTexture name="Signature Stop Sign 40041" x="1153" y="1183.5" width="131.5" height="518" frameX="-442.5" frameY="-69.5" frameWidth="625" frameHeight="1125"/>
	<SubTexture name="Signature Stop Sign 40042" x="1153" y="1183.5" width="131.5" height="518" frameX="-442.5" frameY="-69.5" frameWidth="625" frameHeight="1125"/>
	<SubTexture name="Signature Stop Sign 40043" x="1153" y="1183.5" width="131.5" height="518" frameX="-442.5" frameY="-69.5" frameWidth="625" frameHeight="1125"/>
	<SubTexture name="Signature Stop Sign 40044" x="1153" y="1183.5" width="131.5" height="518" frameX="-442.5" frameY="-69.5" frameWidth="625" frameHeight="1125"/>
	<SubTexture name="Signature Stop Sign 40045" x="1153" y="1183.5" width="131.5" height="518" frameX="-442.5" frameY="-69.5" frameWidth="625" frameHeight="1125"/>
	<SubTexture name="Signature Stop Sign 40046" x="1153" y="1183.5" width="131.5" height="518" frameX="-442.5" frameY="-69.5" frameWidth="625" frameHeight="1125"/>
	<SubTexture name="Signature Stop Sign 40047" x="1153" y="1183.5" width="131.5" height="518" frameX="-442.5" frameY="-69.5" frameWidth="625" frameHeight="1125"/>
	<SubTexture name="Signature Stop Sign 40048" x="1153" y="1183.5" width="131.5" height="518" frameX="-442.5" frameY="-69.5" frameWidth="625" frameHeight="1125"/>
	<SubTexture name="Signature Stop Sign 40049" x="1153" y="1183.5" width="131.5" height="518" frameX="-442.5" frameY="-69.5" frameWidth="625" frameHeight="1125"/>
	<SubTexture name="Signature Stop Sign 40050" x="1153" y="1183.5" width="131.5" height="518" frameX="-442.5" frameY="-69.5" frameWidth="625" frameHeight="1125"/>
	<SubTexture name="Signature Stop Sign 40051" x="1153" y="1183.5" width="131.5" height="518" frameX="-442.5" frameY="-69.5" frameWidth="625" frameHeight="1125"/>
	<SubTexture name="Signature Stop Sign 40052" x="1153" y="1183.5" width="131.5" height="518" frameX="-442.5" frameY="-69.5" frameWidth="625" frameHeight="1125"/>
	<SubTexture name="Signature Stop Sign 40053" x="1153" y="1183.5" width="131.5" height="518" frameX="-442.5" frameY="-69.5" frameWidth="625" frameHeight="1125"/>
	<SubTexture name="Signature Stop Sign 40054" x="1153" y="1183.5" width="131.5" height="518" frameX="-442.5" frameY="-69.5" frameWidth="625" frameHeight="1125"/>
	<SubTexture name="Signature Stop Sign 40055" x="1153" y="1183.5" width="131.5" height="518" frameX="-442.5" frameY="-69.5" frameWidth="625" frameHeight="1125"/>
	<SubTexture name="Signature Stop Sign 40056" x="1153" y="1183.5" width="131.5" height="518" frameX="-442.5" frameY="-69.5" frameWidth="625" frameHeight="1125"/>
	<SubTexture name="Signature Stop Sign 40057" x="1153" y="1183.5" width="131.5" height="518" frameX="-442.5" frameY="-69.5" frameWidth="625" frameHeight="1125"/>
	<SubTexture name="Signature Stop Sign 40058" x="1153" y="1183.5" width="131.5" height="518" frameX="-442.5" frameY="-69.5" frameWidth="625" frameHeight="1125"/>
	<SubTexture name="Signature Stop Sign 40059" x="1153" y="1183.5" width="131.5" height="518" frameX="-442.5" frameY="-69.5" frameWidth="625" frameHeight="1125"/>
	<SubTexture name="Signature Stop Sign 40060" x="1289.5" y="1183.5" width="131.5" height="518" frameX="-444.5" frameY="-68" frameWidth="625" frameHeight="1125"/>
	<SubTexture name="Signature Stop Sign 40061" x="1426" y="1183.5" width="132" height="518.5" frameX="-448" frameY="-65.5" frameWidth="625" frameHeight="1125"/>
	<SubTexture name="Signature Stop Sign 40062" x="1563" y="1183.5" width="135" height="518" frameX="-473.5" frameY="-116.5" frameWidth="625" frameHeight="1125"/>
	<SubTexture name="Signature Stop Sign 40063" x="1703" y="1183.5" width="136.5" height="517.5" frameX="-478.5" frameY="-184.5" frameWidth="625" frameHeight="1125"/>
	<SubTexture name="Signature Stop Sign 40064" x="1844.5" y="1183.5" width="179.5" height="512" frameX="-373" frameY="-334.5" frameWidth="625" frameHeight="1125"/>
	<SubTexture name="Signature Stop Sign 40065" x="1844.5" y="1183.5" width="179.5" height="512" frameX="-372" frameY="-336" frameWidth="625" frameHeight="1125"/>
	<SubTexture name="Signature Stop Sign 40066" x="1844.5" y="1183.5" width="179.5" height="512" frameX="-367" frameY="-340" frameWidth="625" frameHeight="1125"/>
	<SubTexture name="Signature Stop Sign 40067" x="1844.5" y="1183.5" width="179.5" height="512" frameX="-361.5" frameY="-343.5" frameWidth="625" frameHeight="1125"/>
	<SubTexture name="Signature Stop Sign 40068" x="1844.5" y="1183.5" width="179.5" height="512" frameX="-353.5" frameY="-350.5" frameWidth="625" frameHeight="1125"/>
	<SubTexture name="Signature Stop Sign 40069" x="1844.5" y="1183.5" width="179.5" height="512" frameX="-341.5" frameY="-355" frameWidth="625" frameHeight="1125"/>
	<SubTexture name="Signature Stop Sign 40070" x="2029" y="1183.5" width="219" height="502.5" frameX="-228.5" frameY="-332.5" frameWidth="625" frameHeight="1125"/>
	<SubTexture name="Signature Stop Sign 40071" x="2029" y="1183.5" width="219" height="502.5" frameX="-113.5" frameY="-288.5" frameWidth="625" frameHeight="1125"/>
	<SubTexture name="Signature Stop Sign 40072" x="2253" y="1183.5" width="239.5" height="496" frameX="-85.5" frameY="-280.5" frameWidth="625" frameHeight="1125"/>
	<SubTexture name="Signature Stop Sign 40073" x="2497.5" y="1183.5" width="251.5" height="491" frameX="-72.5" frameY="-270" frameWidth="625" frameHeight="1125"/>
	<SubTexture name="Signature Stop Sign 40074" x="2754" y="1183.5" width="261" height="487.5" frameX="-62" frameY="-259.5" frameWidth="625" frameHeight="1125"/>
	<SubTexture name="Signature Stop Sign 40075" x="3020" y="1183.5" width="276" height="480.5" frameX="-49.5" frameY="-251" frameWidth="625" frameHeight="1125"/>
	<SubTexture name="Signature Stop Sign 40076" x="3301" y="1183.5" width="286" height="475" frameX="-47.5" frameY="-247" frameWidth="625" frameHeight="1125"/>
	<SubTexture name="Signature Stop Sign 40077" x="3301" y="1183.5" width="286" height="475" frameX="-59" frameY="-236" frameWidth="625" frameHeight="1125"/>
	<SubTexture name="Signature Stop Sign 40078" x="3301" y="1183.5" width="286" height="475" frameX="-71" frameY="-247.5" frameWidth="625" frameHeight="1125"/>
	<SubTexture name="Signature Stop Sign 40079" x="3301" y="1183.5" width="286" height="475" frameX="-75.5" frameY="-251.5" frameWidth="625" frameHeight="1125"/>
	<SubTexture name="Signature Stop Sign 40080" x="3301" y="1183.5" width="286" height="475" frameX="-85" frameY="-266" frameWidth="625" frameHeight="1125"/>
	<SubTexture name="Signature Stop Sign 40081" x="3301" y="1183.5" width="286" height="475" frameX="-86" frameY="-283.5" frameWidth="625" frameHeight="1125"/>
	<SubTexture name="Signature Stop Sign 40082" x="3301" y="1183.5" width="286" height="475" frameX="-79.5" frameY="-297" frameWidth="625" frameHeight="1125"/>
	<SubTexture name="Signature Stop Sign 40083" x="3301" y="1183.5" width="286" height="475" frameX="-64.5" frameY="-301" frameWidth="625" frameHeight="1125"/>
	<SubTexture name="Signature Stop Sign 40084" x="3592" y="1183.5" width="269" height="483.5" frameX="-68.5" frameY="-287" frameWidth="625" frameHeight="1125"/>
	<SubTexture name="Signature Stop Sign 40085" x="2.5" y="1905.5" width="284" height="476" frameX="-45.5" frameY="-268.5" frameWidth="625" frameHeight="1125"/>
	<SubTexture name="Signature Stop Sign 40086" x="291.5" y="1905.5" width="296" height="469" frameX="-33" frameY="-255" frameWidth="625" frameHeight="1125"/>
	<SubTexture name="Signature Stop Sign 40087" x="3301" y="1183.5" width="286" height="475" frameX="-47.5" frameY="-247" frameWidth="625" frameHeight="1125"/>
	<SubTexture name="Signature Stop Sign 40088" x="3301" y="1183.5" width="286" height="475" frameX="-59" frameY="-236" frameWidth="625" frameHeight="1125"/>
	<SubTexture name="Signature Stop Sign 40089" x="3301" y="1183.5" width="286" height="475" frameX="-71" frameY="-247.5" frameWidth="625" frameHeight="1125"/>
	<SubTexture name="Signature Stop Sign 40090" x="3301" y="1183.5" width="286" height="475" frameX="-75.5" frameY="-251.5" frameWidth="625" frameHeight="1125"/>
	<SubTexture name="Signature Stop Sign 40091" x="3301" y="1183.5" width="286" height="475" frameX="-85" frameY="-266" frameWidth="625" frameHeight="1125"/>
	<SubTexture name="Signature Stop Sign 40092" x="3301" y="1183.5" width="286" height="475" frameX="-86" frameY="-283.5" frameWidth="625" frameHeight="1125"/>
	<SubTexture name="Signature Stop Sign 40093" x="3301" y="1183.5" width="286" height="475" frameX="-79.5" frameY="-297" frameWidth="625" frameHeight="1125"/>
	<SubTexture name="Signature Stop Sign 40094" x="3301" y="1183.5" width="286" height="475" frameX="-64.5" frameY="-301" frameWidth="625" frameHeight="1125"/>
	<SubTexture name="Signature Stop Sign 40095" x="3592" y="1183.5" width="269" height="483.5" frameX="-68.5" frameY="-287" frameWidth="625" frameHeight="1125"/>
	<SubTexture name="Signature Stop Sign 40096" x="2.5" y="1905.5" width="284" height="476" frameX="-45.5" frameY="-268.5" frameWidth="625" frameHeight="1125"/>
	<SubTexture name="Signature Stop Sign 40097" x="291.5" y="1905.5" width="296" height="469" frameX="-33" frameY="-255" frameWidth="625" frameHeight="1125"/>
	<SubTexture name="Signature Stop Sign 40098" x="3301" y="1183.5" width="286" height="475" frameX="-47.5" frameY="-247" frameWidth="625" frameHeight="1125"/>
	<SubTexture name="Signature Stop Sign 40099" x="3301" y="1183.5" width="286" height="475" frameX="-59" frameY="-236" frameWidth="625" frameHeight="1125"/>
	<SubTexture name="Signature Stop Sign 40100" x="3301" y="1183.5" width="286" height="475" frameX="-71" frameY="-247.5" frameWidth="625" frameHeight="1125"/>
	<SubTexture name="Signature Stop Sign 40101" x="3301" y="1183.5" width="286" height="475" frameX="-75.5" frameY="-251.5" frameWidth="625" frameHeight="1125"/>
	<SubTexture name="Signature Stop Sign 40102" x="3301" y="1183.5" width="286" height="475" frameX="-85" frameY="-266" frameWidth="625" frameHeight="1125"/>
	<SubTexture name="Signature Stop Sign 40103" x="3301" y="1183.5" width="286" height="475" frameX="-86" frameY="-283.5" frameWidth="625" frameHeight="1125"/>
	<SubTexture name="Signature Stop Sign 40104" x="3301" y="1183.5" width="286" height="475" frameX="-79.5" frameY="-297" frameWidth="625" frameHeight="1125"/>
	<SubTexture name="Signature Stop Sign 40105" x="3301" y="1183.5" width="286" height="475" frameX="-64.5" frameY="-301" frameWidth="625" frameHeight="1125"/>
	<SubTexture name="Signature Stop Sign 40106" x="3592" y="1183.5" width="269" height="483.5" frameX="-68.5" frameY="-287" frameWidth="625" frameHeight="1125"/>
	<SubTexture name="Signature Stop Sign 40107" x="2.5" y="1905.5" width="284" height="476" frameX="-45.5" frameY="-268.5" frameWidth="625" frameHeight="1125"/>
	<SubTexture name="Signature Stop Sign 40108" x="291.5" y="1905.5" width="296" height="469" frameX="-33" frameY="-255" frameWidth="625" frameHeight="1125"/>
	<SubTexture name="Signature Stop Sign 40109" x="3301" y="1183.5" width="286" height="475" frameX="-47.5" frameY="-247" frameWidth="625" frameHeight="1125"/>
	<SubTexture name="Signature Stop Sign 40110" x="3301" y="1183.5" width="286" height="475" frameX="-59" frameY="-236" frameWidth="625" frameHeight="1125"/>
	<SubTexture name="Signature Stop Sign 40111" x="3301" y="1183.5" width="286" height="475" frameX="-71" frameY="-247.5" frameWidth="625" frameHeight="1125"/>
	<SubTexture name="Signature Stop Sign 40112" x="3301" y="1183.5" width="286" height="475" frameX="-75.5" frameY="-251.5" frameWidth="625" frameHeight="1125"/>
	<SubTexture name="Signature Stop Sign 40113" x="3301" y="1183.5" width="286" height="475" frameX="-85" frameY="-266" frameWidth="625" frameHeight="1125"/>
	<SubTexture name="Signature Stop Sign 40114" x="3301" y="1183.5" width="286" height="475" frameX="-86" frameY="-283.5" frameWidth="625" frameHeight="1125"/>
	<SubTexture name="Signature Stop Sign 40115" x="3301" y="1183.5" width="286" height="475" frameX="-79.5" frameY="-297" frameWidth="625" frameHeight="1125"/>
	<SubTexture name="Signature Stop Sign 40116" x="3301" y="1183.5" width="286" height="475" frameX="-64.5" frameY="-301" frameWidth="625" frameHeight="1125"/>
	<SubTexture name="Signature Stop Sign 40117" x="3592" y="1183.5" width="269" height="483.5" frameX="-68.5" frameY="-287" frameWidth="625" frameHeight="1125"/>
	<SubTexture name="Signature Stop Sign 40118" x="2.5" y="1905.5" width="284" height="476" frameX="-45.5" frameY="-268.5" frameWidth="625" frameHeight="1125"/>
	<SubTexture name="Signature Stop Sign 40119" x="291.5" y="1905.5" width="296" height="469" frameX="-33" frameY="-255" frameWidth="625" frameHeight="1125"/>
	<SubTexture name="Signature Stop Sign 40120" x="3301" y="1183.5" width="286" height="475" frameX="-47.5" frameY="-247" frameWidth="625" frameHeight="1125"/>
	<SubTexture name="Signature Stop Sign 40121" x="3301" y="1183.5" width="286" height="475" frameX="-59" frameY="-236" frameWidth="625" frameHeight="1125"/>
	<SubTexture name="Signature Stop Sign 40122" x="3301" y="1183.5" width="286" height="475" frameX="-71" frameY="-247.5" frameWidth="625" frameHeight="1125"/>
	<SubTexture name="Signature Stop Sign 40123" x="3301" y="1183.5" width="286" height="475" frameX="-75.5" frameY="-251.5" frameWidth="625" frameHeight="1125"/>
	<SubTexture name="Signature Stop Sign 40124" x="3301" y="1183.5" width="286" height="475" frameX="-85" frameY="-266" frameWidth="625" frameHeight="1125"/>
	<SubTexture name="Signature Stop Sign 40125" x="3301" y="1183.5" width="286" height="475" frameX="-86" frameY="-283.5" frameWidth="625" frameHeight="1125"/>
	<SubTexture name="Signature Stop Sign 40126" x="3301" y="1183.5" width="286" height="475" frameX="-79.5" frameY="-297" frameWidth="625" frameHeight="1125"/>
	<SubTexture name="Signature Stop Sign 40127" x="3301" y="1183.5" width="286" height="475" frameX="-64.5" frameY="-301" frameWidth="625" frameHeight="1125"/>
	<SubTexture name="Signature Stop Sign 40128" x="3592" y="1183.5" width="269" height="483.5" frameX="-68.5" frameY="-287" frameWidth="625" frameHeight="1125"/>
	<SubTexture name="Signature Stop Sign 40129" x="2.5" y="1905.5" width="284" height="476" frameX="-45.5" frameY="-268.5" frameWidth="625" frameHeight="1125"/>
	<SubTexture name="Signature Stop Sign 40130" x="291.5" y="1905.5" width="296" height="469" frameX="-33" frameY="-255" frameWidth="625" frameHeight="1125"/>
	<SubTexture name="Signature Stop Sign 40131" x="3301" y="1183.5" width="286" height="475" frameX="-47.5" frameY="-247" frameWidth="625" frameHeight="1125"/>
	<SubTexture name="Signature Stop Sign 40132" x="3301" y="1183.5" width="286" height="475" frameX="-59" frameY="-236" frameWidth="625" frameHeight="1125"/>
	<SubTexture name="Signature Stop Sign 40133" x="3301" y="1183.5" width="286" height="475" frameX="-71" frameY="-247.5" frameWidth="625" frameHeight="1125"/>
	<SubTexture name="Signature Stop Sign 40134" x="3301" y="1183.5" width="286" height="475" frameX="-75.5" frameY="-251.5" frameWidth="625" frameHeight="1125"/>
	<SubTexture name="Signature Stop Sign 40135" x="3301" y="1183.5" width="286" height="475" frameX="-85" frameY="-266" frameWidth="625" frameHeight="1125"/>
	<SubTexture name="Signature Stop Sign 40136" x="3301" y="1183.5" width="286" height="475" frameX="-86" frameY="-283.5" frameWidth="625" frameHeight="1125"/>
	<SubTexture name="Signature Stop Sign 40137" x="3301" y="1183.5" width="286" height="475" frameX="-79.5" frameY="-297" frameWidth="625" frameHeight="1125"/>
	<SubTexture name="Signature Stop Sign 40138" x="3301" y="1183.5" width="286" height="475" frameX="-64.5" frameY="-301" frameWidth="625" frameHeight="1125"/>
	<SubTexture name="Signature Stop Sign 40139" x="3592" y="1183.5" width="269" height="483.5" frameX="-68.5" frameY="-287" frameWidth="625" frameHeight="1125"/>
	<SubTexture name="Signature Stop Sign 40140" x="2.5" y="1905.5" width="284" height="476" frameX="-45.5" frameY="-268.5" frameWidth="625" frameHeight="1125"/>
	<SubTexture name="Signature Stop Sign 40141" x="291.5" y="1905.5" width="296" height="469" frameX="-33" frameY="-255" frameWidth="625" frameHeight="1125"/>
	<SubTexture name="Signature Stop Sign 40142" x="3301" y="1183.5" width="286" height="475" frameX="-47.5" frameY="-247" frameWidth="625" frameHeight="1125"/>
	<SubTexture name="Signature Stop Sign 40143" x="3301" y="1183.5" width="286" height="475" frameX="-59" frameY="-236" frameWidth="625" frameHeight="1125"/>
	<SubTexture name="Signature Stop Sign 40144" x="3301" y="1183.5" width="286" height="475" frameX="-71" frameY="-247.5" frameWidth="625" frameHeight="1125"/>
	<SubTexture name="Signature Stop Sign 40145" x="3301" y="1183.5" width="286" height="475" frameX="-75.5" frameY="-251.5" frameWidth="625" frameHeight="1125"/>
	<SubTexture name="Signature Stop Sign 40146" x="3301" y="1183.5" width="286" height="475" frameX="-85" frameY="-266" frameWidth="625" frameHeight="1125"/>
	<SubTexture name="Signature Stop Sign 40147" x="3301" y="1183.5" width="286" height="475" frameX="-86" frameY="-283.5" frameWidth="625" frameHeight="1125"/>
	<SubTexture name="Signature Stop Sign 40148" x="3301" y="1183.5" width="286" height="475" frameX="-79.5" frameY="-297" frameWidth="625" frameHeight="1125"/>
	<SubTexture name="Signature Stop Sign 40149" x="3301" y="1183.5" width="286" height="475" frameX="-64.5" frameY="-301" frameWidth="625" frameHeight="1125"/>
	<SubTexture name="Signature Stop Sign 40150" x="3592" y="1183.5" width="269" height="483.5" frameX="-68.5" frameY="-287" frameWidth="625" frameHeight="1125"/>
	<SubTexture name="Signature Stop Sign 40151" x="2.5" y="1905.5" width="284" height="476" frameX="-45.5" frameY="-268.5" frameWidth="625" frameHeight="1125"/>
	<SubTexture name="Signature Stop Sign 40152" x="592.5" y="1905.5" width="290.5" height="472" frameX="-38.5" frameY="-265.5" frameWidth="625" frameHeight="1125"/>
	<SubTexture name="Signature Stop Sign 40153" x="888" y="1905.5" width="297" height="469" frameX="-32.5" frameY="-260" frameWidth="625" frameHeight="1125"/>
	<SubTexture name="Signature Stop Sign 40154" x="1190" y="1905.5" width="302" height="466" frameX="-27" frameY="-254" frameWidth="625" frameHeight="1125"/>
	<SubTexture name="Signature Stop Sign 40155" x="1497" y="1905.5" width="306.5" height="463" frameX="-24" frameY="-250.5" frameWidth="625" frameHeight="1125"/>
	<SubTexture name="Signature Stop Sign 40156" x="1808.5" y="1905.5" width="324.5" height="451" frameX="-63.5" frameY="-232" frameWidth="625" frameHeight="1125"/>
	<SubTexture name="Signature Stop Sign 40157" x="1808.5" y="1905.5" width="324.5" height="451" frameX="-71" frameY="-236.5" frameWidth="625" frameHeight="1125"/>
	<SubTexture name="Signature Stop Sign 40158" x="2138" y="1905.5" width="301" height="466.5" frameX="-116.5" frameY="-290.5" frameWidth="625" frameHeight="1125"/>
	<SubTexture name="Signature Stop Sign 40159" x="592.5" y="1905.5" width="290.5" height="472" frameX="-129.5" frameY="-296.5" frameWidth="625" frameHeight="1125"/>
	<SubTexture name="Signature Stop Sign 40160" x="2444" y="1905.5" width="280.5" height="478" frameX="-141.5" frameY="-302" frameWidth="625" frameHeight="1125"/>
	<SubTexture name="Signature Stop Sign 40161" x="2729.5" y="1905.5" width="270.5" height="482.5" frameX="-186.5" frameY="-285.5" frameWidth="625" frameHeight="1125"/>
	<SubTexture name="Signature Stop Sign 40162" x="2729.5" y="1905.5" width="270.5" height="482.5" frameX="-233" frameY="-252" frameWidth="625" frameHeight="1125"/>
	<SubTexture name="Signature Stop Sign 40163" x="3005" y="1905.5" width="262" height="486.5" frameX="-253" frameY="-248.5" frameWidth="625" frameHeight="1125"/>
	<SubTexture name="Signature Stop Sign 40164" x="3272" y="1905.5" width="251.5" height="491" frameX="-269.5" frameY="-243.5" frameWidth="625" frameHeight="1125"/>
	<SubTexture name="Signature Stop Sign 40165" x="3528.5" y="1905.5" width="246.5" height="493" frameX="-282" frameY="-243" frameWidth="625" frameHeight="1125"/>
	<SubTexture name="Signature Stop Sign 40166" x="3780" y="1905.5" width="237.5" height="496.5" frameX="-295.5" frameY="-247.5" frameWidth="625" frameHeight="1125"/>
	<SubTexture name="Signature Stop Sign 40167" x="2.5" y="2407" width="213.5" height="504" frameX="-323" frameY="-310" frameWidth="625" frameHeight="1125"/>
	<SubTexture name="Signature Stop Sign 40168" x="2253" y="1183.5" width="239.5" height="496" frameX="-246" frameY="-350" frameWidth="625" frameHeight="1125"/>
	<SubTexture name="Signature Stop Sign 40169" x="221" y="2407" width="262.5" height="486.5" frameX="-161.5" frameY="-342" frameWidth="625" frameHeight="1125"/>
	<SubTexture name="Signature Stop Sign 40170" x="221" y="2407" width="262.5" height="486.5" frameX="-120.5" frameY="-294" frameWidth="625" frameHeight="1125"/>
	<SubTexture name="Signature Stop Sign 40171" x="488.5" y="2407" width="276" height="480.5" frameX="-150" frameY="-251" frameWidth="625" frameHeight="1125"/>
	<SubTexture name="Signature Stop Sign 40172" x="488.5" y="2407" width="276" height="480.5" frameX="-181" frameY="-232" frameWidth="625" frameHeight="1125"/>
	<SubTexture name="Signature Stop Sign 40173" x="769.5" y="2407" width="251.5" height="491" frameX="-240.5" frameY="-220" frameWidth="625" frameHeight="1125"/>
	<SubTexture name="Signature Stop Sign 40174" x="3272" y="1905.5" width="251.5" height="491" frameX="-269.5" frameY="-243.5" frameWidth="625" frameHeight="1125"/>
	<SubTexture name="Signature Stop Sign 40175" x="3528.5" y="1905.5" width="246.5" height="493" frameX="-282" frameY="-243" frameWidth="625" frameHeight="1125"/>
	<SubTexture name="Signature Stop Sign 40176" x="3780" y="1905.5" width="237.5" height="496.5" frameX="-295.5" frameY="-247.5" frameWidth="625" frameHeight="1125"/>
	<SubTexture name="Signature Stop Sign 40177" x="2.5" y="2407" width="213.5" height="504" frameX="-323" frameY="-310" frameWidth="625" frameHeight="1125"/>
	<SubTexture name="Signature Stop Sign 40178" x="2253" y="1183.5" width="239.5" height="496" frameX="-246" frameY="-350" frameWidth="625" frameHeight="1125"/>
	<SubTexture name="Signature Stop Sign 40179" x="221" y="2407" width="262.5" height="486.5" frameX="-161.5" frameY="-342" frameWidth="625" frameHeight="1125"/>
	<SubTexture name="Signature Stop Sign 40180" x="221" y="2407" width="262.5" height="486.5" frameX="-120.5" frameY="-294" frameWidth="625" frameHeight="1125"/>
	<SubTexture name="Signature Stop Sign 40181" x="488.5" y="2407" width="276" height="480.5" frameX="-150" frameY="-251" frameWidth="625" frameHeight="1125"/>
	<SubTexture name="Signature Stop Sign 40182" x="488.5" y="2407" width="276" height="480.5" frameX="-181" frameY="-232" frameWidth="625" frameHeight="1125"/>
	<SubTexture name="Signature Stop Sign 40183" x="769.5" y="2407" width="251.5" height="491" frameX="-240.5" frameY="-220" frameWidth="625" frameHeight="1125"/>
	<SubTexture name="Signature Stop Sign 40184" x="3272" y="1905.5" width="251.5" height="491" frameX="-269.5" frameY="-243.5" frameWidth="625" frameHeight="1125"/>
	<SubTexture name="Signature Stop Sign 40185" x="3528.5" y="1905.5" width="246.5" height="493" frameX="-282" frameY="-243" frameWidth="625" frameHeight="1125"/>
	<SubTexture name="Signature Stop Sign 40186" x="3780" y="1905.5" width="237.5" height="496.5" frameX="-295.5" frameY="-247.5" frameWidth="625" frameHeight="1125"/>
	<SubTexture name="Signature Stop Sign 40187" x="2.5" y="2407" width="213.5" height="504" frameX="-323" frameY="-310" frameWidth="625" frameHeight="1125"/>
	<SubTexture name="Signature Stop Sign 40188" x="2253" y="1183.5" width="239.5" height="496" frameX="-246" frameY="-350" frameWidth="625" frameHeight="1125"/>
	<SubTexture name="Signature Stop Sign 40189" x="221" y="2407" width="262.5" height="486.5" frameX="-161.5" frameY="-342" frameWidth="625" frameHeight="1125"/>
	<SubTexture name="Signature Stop Sign 40190" x="221" y="2407" width="262.5" height="486.5" frameX="-120.5" frameY="-294" frameWidth="625" frameHeight="1125"/>
	<SubTexture name="Signature Stop Sign 40191" x="488.5" y="2407" width="276" height="480.5" frameX="-150" frameY="-251" frameWidth="625" frameHeight="1125"/>
	<SubTexture name="Signature Stop Sign 40192" x="488.5" y="2407" width="276" height="480.5" frameX="-181" frameY="-232" frameWidth="625" frameHeight="1125"/>
	<SubTexture name="Signature Stop Sign 40193" x="769.5" y="2407" width="251.5" height="491" frameX="-240.5" frameY="-220" frameWidth="625" frameHeight="1125"/>
	<SubTexture name="Signature Stop Sign 40194" x="3272" y="1905.5" width="251.5" height="491" frameX="-269.5" frameY="-243.5" frameWidth="625" frameHeight="1125"/>
	<SubTexture name="Signature Stop Sign 40195" x="3528.5" y="1905.5" width="246.5" height="493" frameX="-282" frameY="-243" frameWidth="625" frameHeight="1125"/>
	<SubTexture name="Signature Stop Sign 40196" x="3780" y="1905.5" width="237.5" height="496.5" frameX="-295.5" frameY="-247.5" frameWidth="625" frameHeight="1125"/>
	<SubTexture name="Signature Stop Sign 40197" x="2.5" y="2407" width="213.5" height="504" frameX="-323" frameY="-310" frameWidth="625" frameHeight="1125"/>
	<SubTexture name="Signature Stop Sign 40198" x="2253" y="1183.5" width="239.5" height="496" frameX="-246" frameY="-350" frameWidth="625" frameHeight="1125"/>
	<SubTexture name="Signature Stop Sign 40199" x="221" y="2407" width="262.5" height="486.5" frameX="-161.5" frameY="-342" frameWidth="625" frameHeight="1125"/>
	<SubTexture name="Signature Stop Sign 40200" x="221" y="2407" width="262.5" height="486.5" frameX="-120.5" frameY="-294" frameWidth="625" frameHeight="1125"/>
	<SubTexture name="Signature Stop Sign 40201" x="488.5" y="2407" width="276" height="480.5" frameX="-150" frameY="-251" frameWidth="625" frameHeight="1125"/>
	<SubTexture name="Signature Stop Sign 40202" x="488.5" y="2407" width="276" height="480.5" frameX="-181" frameY="-232" frameWidth="625" frameHeight="1125"/>
	<SubTexture name="Signature Stop Sign 40203" x="769.5" y="2407" width="251.5" height="491" frameX="-240.5" frameY="-220" frameWidth="625" frameHeight="1125"/>
	<SubTexture name="Signature Stop Sign 40204" x="3272" y="1905.5" width="251.5" height="491" frameX="-269.5" frameY="-243.5" frameWidth="625" frameHeight="1125"/>
	<SubTexture name="Signature Stop Sign 40205" x="3528.5" y="1905.5" width="246.5" height="493" frameX="-282" frameY="-243" frameWidth="625" frameHeight="1125"/>
	<SubTexture name="Signature Stop Sign 40206" x="3780" y="1905.5" width="237.5" height="496.5" frameX="-295.5" frameY="-247.5" frameWidth="625" frameHeight="1125"/>
	<SubTexture name="Signature Stop Sign 40207" x="2.5" y="2407" width="213.5" height="504" frameX="-323" frameY="-310" frameWidth="625" frameHeight="1125"/>
	<SubTexture name="Signature Stop Sign 40208" x="2253" y="1183.5" width="239.5" height="496" frameX="-246" frameY="-350" frameWidth="625" frameHeight="1125"/>
	<SubTexture name="Signature Stop Sign 40209" x="221" y="2407" width="262.5" height="486.5" frameX="-161.5" frameY="-342" frameWidth="625" frameHeight="1125"/>
	<SubTexture name="Signature Stop Sign 40210" x="221" y="2407" width="262.5" height="486.5" frameX="-120.5" frameY="-294" frameWidth="625" frameHeight="1125"/>
	<SubTexture name="Signature Stop Sign 40211" x="488.5" y="2407" width="276" height="480.5" frameX="-150" frameY="-251" frameWidth="625" frameHeight="1125"/>
	<SubTexture name="Signature Stop Sign 40212" x="488.5" y="2407" width="276" height="480.5" frameX="-181" frameY="-232" frameWidth="625" frameHeight="1125"/>
	<SubTexture name="Signature Stop Sign 40213" x="769.5" y="2407" width="251.5" height="491" frameX="-240.5" frameY="-220" frameWidth="625" frameHeight="1125"/>
	<SubTexture name="Signature Stop Sign 40214" x="3272" y="1905.5" width="251.5" height="491" frameX="-269.5" frameY="-243.5" frameWidth="625" frameHeight="1125"/>
	<SubTexture name="Signature Stop Sign 40215" x="3528.5" y="1905.5" width="246.5" height="493" frameX="-282" frameY="-243" frameWidth="625" frameHeight="1125"/>
	<SubTexture name="Signature Stop Sign 40216" x="3780" y="1905.5" width="237.5" height="496.5" frameX="-295.5" frameY="-247.5" frameWidth="625" frameHeight="1125"/>
	<SubTexture name="Signature Stop Sign 40217" x="2.5" y="2407" width="213.5" height="504" frameX="-323" frameY="-310" frameWidth="625" frameHeight="1125"/>
	<SubTexture name="Signature Stop Sign 40218" x="2253" y="1183.5" width="239.5" height="496" frameX="-246" frameY="-350" frameWidth="625" frameHeight="1125"/>
	<SubTexture name="Signature Stop Sign 40219" x="221" y="2407" width="262.5" height="486.5" frameX="-161.5" frameY="-342" frameWidth="625" frameHeight="1125"/>
	<SubTexture name="Signature Stop Sign 40220" x="221" y="2407" width="262.5" height="486.5" frameX="-120.5" frameY="-294" frameWidth="625" frameHeight="1125"/>
	<SubTexture name="Signature Stop Sign 40221" x="488.5" y="2407" width="276" height="480.5" frameX="-150" frameY="-251" frameWidth="625" frameHeight="1125"/>
	<SubTexture name="Signature Stop Sign 40222" x="488.5" y="2407" width="276" height="480.5" frameX="-181" frameY="-232" frameWidth="625" frameHeight="1125"/>
	<SubTexture name="Signature Stop Sign 40223" x="769.5" y="2407" width="251.5" height="491" frameX="-240.5" frameY="-220" frameWidth="625" frameHeight="1125"/>
	<SubTexture name="Signature Stop Sign 40224" x="3272" y="1905.5" width="251.5" height="491" frameX="-269.5" frameY="-243.5" frameWidth="625" frameHeight="1125"/>
	<SubTexture name="Signature Stop Sign 40225" x="3528.5" y="1905.5" width="246.5" height="493" frameX="-282" frameY="-243" frameWidth="625" frameHeight="1125"/>
	<SubTexture name="Signature Stop Sign 40226" x="3780" y="1905.5" width="237.5" height="496.5" frameX="-295.5" frameY="-247.5" frameWidth="625" frameHeight="1125"/>
	<SubTexture name="Signature Stop Sign 40227" x="2.5" y="2407" width="213.5" height="504" frameX="-323" frameY="-310" frameWidth="625" frameHeight="1125"/>
	<SubTexture name="Signature Stop Sign 40228" x="2253" y="1183.5" width="239.5" height="496" frameX="-246" frameY="-350" frameWidth="625" frameHeight="1125"/>
	<SubTexture name="Signature Stop Sign 40229" x="2253" y="1183.5" width="239.5" height="496" frameX="-166.5" frameY="-397.5" frameWidth="625" frameHeight="1125"/>
	<SubTexture name="Signature Stop Sign 40230" x="2253" y="1183.5" width="239.5" height="496" frameX="-81" frameY="-452.5" frameWidth="625" frameHeight="1125"/>
	<SubTexture name="Signature Stop Sign 40231" x="2253" y="1183.5" width="239.5" height="496" frameX="0" frameY="-498.5" frameWidth="625" frameHeight="1125"/>
	<SubTexture name="Signature Stop Sign 40232" x="2253" y="1183.5" width="239.5" height="496" frameX="0" frameY="-498.5" frameWidth="625" frameHeight="1125"/>
	<SubTexture name="Signature Stop Sign 40233" x="2253" y="1183.5" width="239.5" height="496" frameX="0" frameY="-498.5" frameWidth="625" frameHeight="1125"/>
</TextureAtlas>
