<?xml version="1.0" encoding="utf-8"?>
<TextureAtlas imagePath="Le_corrrupt_Bf.png">
	<!-- Created with Adobe Animate version 21.0.6.41649 -->
	<!-- http://www.adobe.com/products/animate.html -->
	<SubTexture name="BF NOTE DOWN0000" x="0" y="0" width="377" height="370" frameX="-1" frameY="-6" frameWidth="379" frameHeight="383"/>
	<SubTexture name="BF NOTE DOWN0001" x="377" y="0" width="378" height="374" frameX="-1" frameY="-5" frameWidth="379" frameHeight="383"/>
	<SubTexture name="BF NOTE DOWN0002" x="755" y="0" width="379" height="378" frameX="0" frameY="-1" frameWidth="379" frameHeight="383"/>
	<SubTexture name="BF NOTE DOWN0003" x="1134" y="0" width="378" height="383" frameX="0" frameY="0" frameWidth="379" frameHeight="383"/>
	<SubTexture name="BF NOTE DOWN0004" x="1512" y="0" width="378" height="383" frameX="0" frameY="0" frameWidth="379" frameHeight="383"/>
	<SubTexture name="BF NOTE DOWN0005" x="1890" y="0" width="378" height="376" frameX="0" frameY="0" frameWidth="379" frameHeight="383"/>
	<SubTexture name="BF NOTE DOWN0006" x="2268" y="0" width="379" height="379" frameX="0" frameY="0" frameWidth="379" frameHeight="383"/>
	<SubTexture name="BF NOTE DOWN0007" x="2647" y="0" width="379" height="379" frameX="0" frameY="0" frameWidth="379" frameHeight="383"/>
	<SubTexture name="BF NOTE DOWN0008" x="3026" y="0" width="378" height="383" frameX="0" frameY="0" frameWidth="379" frameHeight="383"/>
	<SubTexture name="BF NOTE DOWN0009" x="3404" y="0" width="378" height="383" frameX="0" frameY="0" frameWidth="379" frameHeight="383"/>
	<SubTexture name="BF NOTE DOWN0010" x="0" y="383" width="378" height="376" frameX="0" frameY="0" frameWidth="379" frameHeight="383"/>
	<SubTexture name="BF NOTE DOWN0011" x="378" y="383" width="379" height="379" frameX="0" frameY="0" frameWidth="379" frameHeight="383"/>
	<SubTexture name="BF NOTE DOWN0012" x="2268" y="0" width="379" height="379" frameX="0" frameY="0" frameWidth="379" frameHeight="383"/>
	<SubTexture name="BF NOTE DOWN0013" x="3404" y="0" width="378" height="383" frameX="0" frameY="0" frameWidth="379" frameHeight="383"/>
	<SubTexture name="BF NOTE DOWN0014" x="3026" y="0" width="378" height="383" frameX="0" frameY="0" frameWidth="379" frameHeight="383"/>
	<SubTexture name="BF NOTE DOWN0015" x="757" y="383" width="378" height="376" frameX="0" frameY="0" frameWidth="379" frameHeight="383"/>
	<SubTexture name="BF NOTE DOWN0016" x="2268" y="0" width="379" height="379" frameX="0" frameY="0" frameWidth="379" frameHeight="383"/>
	<SubTexture name="BF NOTE DOWN0017" x="378" y="383" width="379" height="379" frameX="0" frameY="0" frameWidth="379" frameHeight="383"/>
	<SubTexture name="BF NOTE DOWN0018" x="1512" y="0" width="378" height="383" frameX="0" frameY="0" frameWidth="379" frameHeight="383"/>
	<SubTexture name="BF NOTE DOWN0019" x="3404" y="0" width="378" height="383" frameX="0" frameY="0" frameWidth="379" frameHeight="383"/>
	<SubTexture name="BF NOTE DOWN0020" x="1135" y="383" width="378" height="376" frameX="0" frameY="0" frameWidth="379" frameHeight="383"/>
	<SubTexture name="BF NOTE DOWN0021" x="2647" y="0" width="379" height="379" frameX="0" frameY="0" frameWidth="379" frameHeight="383"/>
	<SubTexture name="BF NOTE DOWN0022" x="2268" y="0" width="379" height="379" frameX="0" frameY="0" frameWidth="379" frameHeight="383"/>
	<SubTexture name="BF NOTE DOWN0023" x="1513" y="383" width="378" height="383" frameX="0" frameY="0" frameWidth="379" frameHeight="383"/>
	<SubTexture name="BF NOTE DOWN0024" x="1512" y="0" width="378" height="383" frameX="0" frameY="0" frameWidth="379" frameHeight="383"/>
	<SubTexture name="BF NOTE DOWN0025" x="757" y="383" width="378" height="376" frameX="0" frameY="0" frameWidth="379" frameHeight="383"/>
	<SubTexture name="BF NOTE DOWN0026" x="1891" y="383" width="379" height="379" frameX="0" frameY="0" frameWidth="379" frameHeight="383"/>
	<SubTexture name="BF NOTE DOWN0027" x="2647" y="0" width="379" height="379" frameX="0" frameY="0" frameWidth="379" frameHeight="383"/>
	<SubTexture name="BF NOTE DOWN0028" x="1512" y="0" width="378" height="383" frameX="0" frameY="0" frameWidth="379" frameHeight="383"/>
	<SubTexture name="BF NOTE DOWN0029" x="1513" y="383" width="378" height="383" frameX="0" frameY="0" frameWidth="379" frameHeight="383"/>
	<SubTexture name="BF NOTE LEFT0000" x="2270" y="383" width="389" height="414" frameX="0" frameY="0" frameWidth="390" frameHeight="420"/>
	<SubTexture name="BF NOTE LEFT0001" x="2659" y="383" width="390" height="417" frameX="0" frameY="0" frameWidth="390" frameHeight="420"/>
	<SubTexture name="BF NOTE LEFT0002" x="3049" y="383" width="379" height="414" frameX="-11" frameY="-3" frameWidth="390" frameHeight="420"/>
	<SubTexture name="BF NOTE LEFT0003" x="3428" y="383" width="375" height="416" frameX="-14" frameY="-4" frameWidth="390" frameHeight="420"/>
	<SubTexture name="BF NOTE LEFT0004" x="0" y="800" width="373" height="416" frameX="-16" frameY="-4" frameWidth="390" frameHeight="420"/>
	<SubTexture name="BF NOTE LEFT0005" x="373" y="800" width="380" height="410" frameX="-9" frameY="-4" frameWidth="390" frameHeight="420"/>
	<SubTexture name="BF NOTE LEFT0006" x="753" y="800" width="374" height="413" frameX="-16" frameY="-4" frameWidth="390" frameHeight="420"/>
	<SubTexture name="BF NOTE LEFT0007" x="1127" y="800" width="373" height="413" frameX="-17" frameY="-4" frameWidth="390" frameHeight="420"/>
	<SubTexture name="BF NOTE LEFT0008" x="1500" y="800" width="373" height="416" frameX="-16" frameY="-4" frameWidth="390" frameHeight="420"/>
	<SubTexture name="BF NOTE LEFT0009" x="1873" y="800" width="372" height="416" frameX="-17" frameY="-4" frameWidth="390" frameHeight="420"/>
	<SubTexture name="BF NOTE LEFT0010" x="2245" y="800" width="380" height="410" frameX="-9" frameY="-4" frameWidth="390" frameHeight="420"/>
	<SubTexture name="BF NOTE LEFT0011" x="2625" y="800" width="373" height="413" frameX="-17" frameY="-4" frameWidth="390" frameHeight="420"/>
	<SubTexture name="BF NOTE LEFT0012" x="753" y="800" width="374" height="413" frameX="-16" frameY="-4" frameWidth="390" frameHeight="420"/>
	<SubTexture name="BF NOTE LEFT0013" x="2998" y="800" width="372" height="416" frameX="-17" frameY="-4" frameWidth="390" frameHeight="420"/>
	<SubTexture name="BF NOTE LEFT0014" x="3370" y="800" width="378" height="418" frameX="-11" frameY="-2" frameWidth="390" frameHeight="420"/>
	<SubTexture name="BF NOTE RIGHT0000" x="0" y="1218" width="408" height="415" frameX="-1" frameY="-2" frameWidth="409" frameHeight="424"/>
	<SubTexture name="BF NOTE RIGHT0001" x="408" y="1218" width="408" height="418" frameX="-1" frameY="-2" frameWidth="409" frameHeight="424"/>
	<SubTexture name="BF NOTE RIGHT0002" x="816" y="1218" width="408" height="420" frameX="0" frameY="0" frameWidth="409" frameHeight="424"/>
	<SubTexture name="BF NOTE RIGHT0003" x="1224" y="1218" width="403" height="424" frameX="0" frameY="0" frameWidth="409" frameHeight="424"/>
	<SubTexture name="BF NOTE RIGHT0004" x="1627" y="1218" width="398" height="424" frameX="0" frameY="0" frameWidth="409" frameHeight="424"/>
	<SubTexture name="BF NOTE RIGHT0005" x="2025" y="1218" width="397" height="417" frameX="0" frameY="0" frameWidth="409" frameHeight="424"/>
	<SubTexture name="BF NOTE RIGHT0006" x="2422" y="1218" width="398" height="420" frameX="0" frameY="0" frameWidth="409" frameHeight="424"/>
	<SubTexture name="BF NOTE RIGHT0007" x="2820" y="1218" width="397" height="420" frameX="0" frameY="0" frameWidth="409" frameHeight="424"/>
	<SubTexture name="BF NOTE RIGHT0008" x="3217" y="1218" width="398" height="424" frameX="0" frameY="0" frameWidth="409" frameHeight="424"/>
	<SubTexture name="BF NOTE RIGHT0009" x="3615" y="1218" width="397" height="424" frameX="0" frameY="0" frameWidth="409" frameHeight="424"/>
	<SubTexture name="BF NOTE RIGHT0010" x="0" y="1642" width="398" height="417" frameX="0" frameY="0" frameWidth="409" frameHeight="424"/>
	<SubTexture name="BF NOTE RIGHT0011" x="398" y="1642" width="397" height="420" frameX="0" frameY="0" frameWidth="409" frameHeight="424"/>
	<SubTexture name="BF NOTE RIGHT0012" x="2422" y="1218" width="398" height="420" frameX="0" frameY="0" frameWidth="409" frameHeight="424"/>
	<SubTexture name="BF NOTE RIGHT0013" x="3615" y="1218" width="397" height="424" frameX="0" frameY="0" frameWidth="409" frameHeight="424"/>
	<SubTexture name="BF NOTE RIGHT0014" x="3217" y="1218" width="398" height="424" frameX="0" frameY="0" frameWidth="409" frameHeight="424"/>
	<SubTexture name="BF NOTE RIGHT0015" x="795" y="1642" width="397" height="417" frameX="0" frameY="0" frameWidth="409" frameHeight="424"/>
	<SubTexture name="BF NOTE RIGHT0016" x="2422" y="1218" width="398" height="420" frameX="0" frameY="0" frameWidth="409" frameHeight="424"/>
	<SubTexture name="BF NOTE RIGHT0017" x="398" y="1642" width="397" height="420" frameX="0" frameY="0" frameWidth="409" frameHeight="424"/>
	<SubTexture name="BF NOTE RIGHT0018" x="1627" y="1218" width="398" height="424" frameX="0" frameY="0" frameWidth="409" frameHeight="424"/>
	<SubTexture name="BF NOTE RIGHT0019" x="3615" y="1218" width="397" height="424" frameX="0" frameY="0" frameWidth="409" frameHeight="424"/>
	<SubTexture name="BF NOTE RIGHT0020" x="1192" y="1642" width="398" height="417" frameX="0" frameY="0" frameWidth="409" frameHeight="424"/>
	<SubTexture name="BF NOTE RIGHT0021" x="2820" y="1218" width="397" height="420" frameX="0" frameY="0" frameWidth="409" frameHeight="424"/>
	<SubTexture name="BF NOTE RIGHT0022" x="2422" y="1218" width="398" height="420" frameX="0" frameY="0" frameWidth="409" frameHeight="424"/>
	<SubTexture name="BF NOTE RIGHT0023" x="1590" y="1642" width="397" height="424" frameX="0" frameY="0" frameWidth="409" frameHeight="424"/>
	<SubTexture name="BF NOTE RIGHT0024" x="1627" y="1218" width="398" height="424" frameX="0" frameY="0" frameWidth="409" frameHeight="424"/>
	<SubTexture name="BF NOTE RIGHT0025" x="795" y="1642" width="397" height="417" frameX="0" frameY="0" frameWidth="409" frameHeight="424"/>
	<SubTexture name="BF NOTE RIGHT0026" x="1987" y="1642" width="398" height="420" frameX="0" frameY="0" frameWidth="409" frameHeight="424"/>
	<SubTexture name="BF NOTE RIGHT0027" x="2820" y="1218" width="397" height="420" frameX="0" frameY="0" frameWidth="409" frameHeight="424"/>
	<SubTexture name="BF NOTE RIGHT0028" x="1627" y="1218" width="398" height="424" frameX="0" frameY="0" frameWidth="409" frameHeight="424"/>
	<SubTexture name="BF NOTE RIGHT0029" x="1590" y="1642" width="397" height="424" frameX="0" frameY="0" frameWidth="409" frameHeight="424"/>
	<SubTexture name="BF NOTE RIGHT0030" x="0" y="1642" width="398" height="417" frameX="0" frameY="0" frameWidth="409" frameHeight="424"/>
	<SubTexture name="BF NOTE RIGHT0031" x="2820" y="1218" width="397" height="420" frameX="0" frameY="0" frameWidth="409" frameHeight="424"/>
	<SubTexture name="BF NOTE RIGHT0032" x="1987" y="1642" width="398" height="420" frameX="0" frameY="0" frameWidth="409" frameHeight="424"/>
	<SubTexture name="BF NOTE RIGHT0033" x="3615" y="1218" width="397" height="424" frameX="0" frameY="0" frameWidth="409" frameHeight="424"/>
	<SubTexture name="BF NOTE RIGHT0034" x="1627" y="1218" width="398" height="424" frameX="0" frameY="0" frameWidth="409" frameHeight="424"/>
	<SubTexture name="BF NOTE RIGHT0035" x="2025" y="1218" width="397" height="417" frameX="0" frameY="0" frameWidth="409" frameHeight="424"/>
	<SubTexture name="BF NOTE RIGHT0036" x="2422" y="1218" width="398" height="420" frameX="0" frameY="0" frameWidth="409" frameHeight="424"/>
	<SubTexture name="BF NOTE RIGHT0037" x="2820" y="1218" width="397" height="420" frameX="0" frameY="0" frameWidth="409" frameHeight="424"/>
	<SubTexture name="BF NOTE RIGHT0038" x="3217" y="1218" width="398" height="424" frameX="0" frameY="0" frameWidth="409" frameHeight="424"/>
	<SubTexture name="BF NOTE RIGHT0039" x="3615" y="1218" width="397" height="424" frameX="0" frameY="0" frameWidth="409" frameHeight="424"/>
	<SubTexture name="BF NOTE RIGHT0040" x="0" y="1642" width="398" height="417" frameX="0" frameY="0" frameWidth="409" frameHeight="424"/>
	<SubTexture name="BF NOTE RIGHT0041" x="398" y="1642" width="397" height="420" frameX="0" frameY="0" frameWidth="409" frameHeight="424"/>
	<SubTexture name="BF NOTE RIGHT0042" x="2422" y="1218" width="398" height="420" frameX="0" frameY="0" frameWidth="409" frameHeight="424"/>
	<SubTexture name="BF NOTE RIGHT0043" x="3615" y="1218" width="397" height="424" frameX="0" frameY="0" frameWidth="409" frameHeight="424"/>
	<SubTexture name="BF NOTE RIGHT0044" x="3217" y="1218" width="398" height="424" frameX="0" frameY="0" frameWidth="409" frameHeight="424"/>
	<SubTexture name="BF NOTE RIGHT0045" x="795" y="1642" width="397" height="417" frameX="0" frameY="0" frameWidth="409" frameHeight="424"/>
	<SubTexture name="BF NOTE RIGHT0046" x="2422" y="1218" width="398" height="420" frameX="0" frameY="0" frameWidth="409" frameHeight="424"/>
	<SubTexture name="BF NOTE RIGHT0047" x="398" y="1642" width="397" height="420" frameX="0" frameY="0" frameWidth="409" frameHeight="424"/>
	<SubTexture name="BF NOTE RIGHT0048" x="1627" y="1218" width="398" height="424" frameX="0" frameY="0" frameWidth="409" frameHeight="424"/>
	<SubTexture name="BF NOTE RIGHT0049" x="3615" y="1218" width="397" height="424" frameX="0" frameY="0" frameWidth="409" frameHeight="424"/>
	<SubTexture name="BF NOTE RIGHT0050" x="1192" y="1642" width="398" height="417" frameX="0" frameY="0" frameWidth="409" frameHeight="424"/>
	<SubTexture name="BF NOTE RIGHT0051" x="2820" y="1218" width="397" height="420" frameX="0" frameY="0" frameWidth="409" frameHeight="424"/>
	<SubTexture name="BF NOTE RIGHT0052" x="2422" y="1218" width="398" height="420" frameX="0" frameY="0" frameWidth="409" frameHeight="424"/>
	<SubTexture name="BF NOTE RIGHT0053" x="1590" y="1642" width="397" height="424" frameX="0" frameY="0" frameWidth="409" frameHeight="424"/>
	<SubTexture name="BF NOTE RIGHT0054" x="1627" y="1218" width="398" height="424" frameX="0" frameY="0" frameWidth="409" frameHeight="424"/>
	<SubTexture name="BF NOTE RIGHT0055" x="795" y="1642" width="397" height="417" frameX="0" frameY="0" frameWidth="409" frameHeight="424"/>
	<SubTexture name="BF NOTE RIGHT0056" x="1987" y="1642" width="398" height="420" frameX="0" frameY="0" frameWidth="409" frameHeight="424"/>
	<SubTexture name="BF NOTE RIGHT0057" x="2820" y="1218" width="397" height="420" frameX="0" frameY="0" frameWidth="409" frameHeight="424"/>
	<SubTexture name="BF NOTE RIGHT0058" x="1627" y="1218" width="398" height="424" frameX="0" frameY="0" frameWidth="409" frameHeight="424"/>
	<SubTexture name="BF NOTE RIGHT0059" x="1590" y="1642" width="397" height="424" frameX="0" frameY="0" frameWidth="409" frameHeight="424"/>
	<SubTexture name="BF NOTE RIGHT0060" x="0" y="1642" width="398" height="417" frameX="0" frameY="0" frameWidth="409" frameHeight="424"/>
	<SubTexture name="BF NOTE RIGHT0061" x="2820" y="1218" width="397" height="420" frameX="0" frameY="0" frameWidth="409" frameHeight="424"/>
	<SubTexture name="BF NOTE UP0000" x="2385" y="1642" width="370" height="453" frameX="-7" frameY="0" frameWidth="379" frameHeight="459"/>
	<SubTexture name="BF NOTE UP0001" x="2755" y="1642" width="368" height="455" frameX="-8" frameY="0" frameWidth="379" frameHeight="459"/>
	<SubTexture name="BF NOTE UP0002" x="3123" y="1642" width="376" height="450" frameX="-3" frameY="-5" frameWidth="379" frameHeight="459"/>
	<SubTexture name="BF NOTE UP0003" x="3499" y="1642" width="375" height="454" frameX="-2" frameY="-5" frameWidth="379" frameHeight="459"/>
	<SubTexture name="BF NOTE UP0004" x="0" y="2097" width="379" height="454" frameX="0" frameY="-5" frameWidth="379" frameHeight="459"/>
	<SubTexture name="BF NOTE UP0005" x="379" y="2097" width="376" height="448" frameX="-1" frameY="-5" frameWidth="379" frameHeight="459"/>
	<SubTexture name="BF NOTE UP0006" x="755" y="2097" width="379" height="450" frameX="0" frameY="-5" frameWidth="379" frameHeight="459"/>
	<SubTexture name="BF NOTE UP0007" x="1134" y="2097" width="376" height="450" frameX="-1" frameY="-5" frameWidth="379" frameHeight="459"/>
	<SubTexture name="BF NOTE UP0008" x="1510" y="2097" width="379" height="454" frameX="0" frameY="-5" frameWidth="379" frameHeight="459"/>
	<SubTexture name="BF NOTE UP0009" x="1889" y="2097" width="376" height="454" frameX="-1" frameY="-5" frameWidth="379" frameHeight="459"/>
	<SubTexture name="BF NOTE UP0010" x="2265" y="2097" width="379" height="448" frameX="0" frameY="-5" frameWidth="379" frameHeight="459"/>
	<SubTexture name="BF NOTE UP0011" x="2644" y="2097" width="376" height="450" frameX="-1" frameY="-5" frameWidth="379" frameHeight="459"/>
	<SubTexture name="BF NOTE UP0012" x="755" y="2097" width="379" height="450" frameX="0" frameY="-5" frameWidth="379" frameHeight="459"/>
	<SubTexture name="BF NOTE UP0013" x="1889" y="2097" width="376" height="454" frameX="-1" frameY="-5" frameWidth="379" frameHeight="459"/>
	<SubTexture name="BF NOTE UP0014" x="1510" y="2097" width="379" height="454" frameX="0" frameY="-5" frameWidth="379" frameHeight="459"/>
	<SubTexture name="BF idle dance0000" x="3020" y="2097" width="418" height="400" frameX="0" frameY="-21" frameWidth="422" frameHeight="427"/>
	<SubTexture name="BF idle dance0001" x="3438" y="2097" width="416" height="402" frameX="-1" frameY="-21" frameWidth="422" frameHeight="427"/>
	<SubTexture name="BF idle dance0002" x="0" y="2551" width="418" height="403" frameX="-1" frameY="-20" frameWidth="422" frameHeight="427"/>
	<SubTexture name="BF idle dance0003" x="418" y="2551" width="418" height="407" frameX="-1" frameY="-20" frameWidth="422" frameHeight="427"/>
	<SubTexture name="BF idle dance0004" x="836" y="2551" width="413" height="412" frameX="-6" frameY="-15" frameWidth="422" frameHeight="427"/>
	<SubTexture name="BF idle dance0005" x="1249" y="2551" width="413" height="407" frameX="-6" frameY="-14" frameWidth="422" frameHeight="427"/>
	<SubTexture name="BF idle dance0006" x="1662" y="2551" width="413" height="421" frameX="-9" frameY="-2" frameWidth="422" frameHeight="427"/>
	<SubTexture name="BF idle dance0007" x="2075" y="2551" width="411" height="421" frameX="-10" frameY="-2" frameWidth="422" frameHeight="427"/>
	<SubTexture name="BF idle dance0008" x="2486" y="2551" width="412" height="426" frameX="-9" frameY="-1" frameWidth="422" frameHeight="427"/>
	<SubTexture name="BF idle dance0009" x="2898" y="2551" width="412" height="427" frameX="-9" frameY="0" frameWidth="422" frameHeight="427"/>
	<SubTexture name="BF idle dance0010" x="3310" y="2551" width="412" height="420" frameX="-9" frameY="-1" frameWidth="422" frameHeight="427"/>
	<SubTexture name="BF idle dance0011" x="0" y="2978" width="412" height="423" frameX="-9" frameY="0" frameWidth="422" frameHeight="427"/>
	<SubTexture name="BF idle dance0012" x="412" y="2978" width="412" height="422" frameX="-9" frameY="-1" frameWidth="422" frameHeight="427"/>
	<SubTexture name="BF idle dance0013" x="2898" y="2551" width="412" height="427" frameX="-9" frameY="0" frameWidth="422" frameHeight="427"/>
</TextureAtlas>
