{
	"animations": [
		{
			"offsets": [
				-2,
				0
			],
			"loop": false,
			"fps": 24,
			"anim": "idle",
			"indices": [],
			"name": "idle"
		},
		{
			"offsets": [
				-40,
				-13
			],
			"loop": false,
			"fps": 24,
			"anim": "singRIGHT",
			"indices": [],
			"name": "right"
		},
		{
			"offsets": [
				73,
				-10
			],
			"loop": false,
			"fps": 24,
			"anim": "singLEFT",
			"indices": [],
			"name": "left"
		},
		{
			"offsets": [
				-10,
				-38
			],
			"loop": false,
			"fps": 24,
			"anim": "singDOWN",
			"indices": [],
			"name": "down"
		},
		{
			"offsets": [
				34,
				-20
			],
			"loop": false,
			"fps": 24,
			"anim": "singUP",
			"indices": [],
			"name": "up"
		}
	],
	"no_antialiasing": false,
	"image": "characters/cosmo",
	"position": [
		-260,
		30
	],
	"healthicon": "wanda-cosmo",
	"flip_x": false,
	"healthbar_colors": [
		112,
		0,
		155
	],
	"camera_position": [
		140,
		190
	],
	"sing_duration": 6.1,
	"scale": 1
}