<?xml version="1.0" encoding="utf-8"?>
<TextureAtlas imagePath="parents.png">
	<!-- Created with Adobe Animate version 22.0.3.179 -->
	<!-- http://www.adobe.com/products/animate.html -->
	<SubTexture name="dadAppear0000" x="10" y="10" width="50" height="82" frameX="-260" frameY="-157" frameWidth="1409" frameHeight="654"/>
	<SubTexture name="dadAppear0001" x="70" y="10" width="55" height="92" frameX="-270" frameY="-94" frameWidth="1409" frameHeight="654"/>
	<SubTexture name="dadAppear0002" x="135" y="10" width="57" height="95" frameX="-274" frameY="-71" frameWidth="1409" frameHeight="654"/>
	<SubTexture name="dadAppear0003" x="202" y="10" width="59" height="98" frameX="-276" frameY="-54" frameWidth="1409" frameHeight="654"/>
	<SubTexture name="dadAppear0004" x="271" y="10" width="60" height="100" frameX="-278" frameY="-42" frameWidth="1409" frameHeight="654"/>
	<SubTexture name="dadAppear0005" x="341" y="10" width="61" height="102" frameX="-280" frameY="-32" frameWidth="1409" frameHeight="654"/>
	<SubTexture name="dadAppear0006" x="412" y="10" width="61" height="102" frameX="-281" frameY="-25" frameWidth="1409" frameHeight="654"/>
	<SubTexture name="dadAppear0007" x="483" y="10" width="62" height="103" frameX="-282" frameY="-20" frameWidth="1409" frameHeight="654"/>
	<SubTexture name="dadAppear0008" x="555" y="10" width="63" height="104" frameX="-282" frameY="-16" frameWidth="1409" frameHeight="654"/>
	<SubTexture name="dadAppear0009" x="628" y="10" width="63" height="104" frameX="-282" frameY="-14" frameWidth="1409" frameHeight="654"/>
	<SubTexture name="dadAppear0010" x="701" y="10" width="62" height="104" frameX="-283" frameY="-13" frameWidth="1409" frameHeight="654"/>
	<SubTexture name="dadAppear0011" x="701" y="10" width="62" height="104" frameX="-283" frameY="-11" frameWidth="1409" frameHeight="654"/>
	<SubTexture name="dadAppear0012" x="773" y="10" width="62" height="96" frameX="-283" frameY="-8" frameWidth="1409" frameHeight="654"/>
	<SubTexture name="dadAppear0013" x="845" y="10" width="62" height="93" frameX="-283" frameY="-4" frameWidth="1409" frameHeight="654"/>
	<SubTexture name="dadAppear0014" x="917" y="10" width="252" height="130" frameX="-220" frameY="0" frameWidth="1409" frameHeight="654"/>
	<SubTexture name="dadAppear0015" x="1179" y="10" width="583" height="320" frameX="-212" frameY="-44" frameWidth="1409" frameHeight="654"/>
	<SubTexture name="dadAppear0016" x="1772" y="10" width="851" height="434" frameX="-187" frameY="-90" frameWidth="1409" frameHeight="654"/>
	<SubTexture name="dadAppear0017" x="2633" y="10" width="1010" height="490" frameX="-170" frameY="-122" frameWidth="1409" frameHeight="654"/>
	<SubTexture name="dadAppear0018" x="3653" y="10" width="1079" height="511" frameX="-163" frameY="-138" frameWidth="1409" frameHeight="654"/>
	<SubTexture name="dadAppear0019" x="4742" y="10" width="1087" height="514" frameX="-162" frameY="-140" frameWidth="1409" frameHeight="654"/>
	<SubTexture name="dadAppear0020" x="5839" y="10" width="1059" height="505" frameX="-165" frameY="-134" frameWidth="1409" frameHeight="654"/>
	<SubTexture name="dadAppear0021" x="6908" y="10" width="1023" height="493" frameX="-169" frameY="-126" frameWidth="1409" frameHeight="654"/>
	<SubTexture name="dadAppear0022" x="10" y="534" width="1006" height="487" frameX="-171" frameY="-122" frameWidth="1409" frameHeight="654"/>
	<SubTexture name="dadAppear0023" x="1026" y="534" width="1113" height="455" frameX="-92" frameY="-134" frameWidth="1409" frameHeight="654"/>
	<SubTexture name="dadAppear0024" x="2149" y="534" width="1212" height="430" frameX="-26" frameY="-133" frameWidth="1409" frameHeight="654"/>
	<SubTexture name="dadAppear0025" x="3371" y="534" width="1232" height="429" frameX="-4" frameY="-123" frameWidth="1409" frameHeight="654"/>
	<SubTexture name="dadAppear0026" x="4613" y="534" width="1178" height="419" frameX="-23" frameY="-132" frameWidth="1409" frameHeight="654"/>
	<SubTexture name="dadAppear0027" x="5801" y="534" width="1224" height="426" frameX="-3" frameY="-123" frameWidth="1409" frameHeight="654"/>
	<SubTexture name="dadAppear0028" x="10" y="1031" width="1224" height="426" frameX="-3" frameY="-123" frameWidth="1409" frameHeight="654"/>
	<SubTexture name="dadAppear0029" x="1244" y="1031" width="1026" height="472" frameX="-91" frameY="-78" frameWidth="1409" frameHeight="654"/>
	<SubTexture name="dadAppear0030" x="2280" y="1031" width="907" height="441" frameX="-145" frameY="-120" frameWidth="1409" frameHeight="654"/>
	<SubTexture name="dadAppear0031" x="3197" y="1031" width="1189" height="423" frameX="-23" frameY="-132" frameWidth="1409" frameHeight="654"/>
	<SubTexture name="dadAppear0032" x="4396" y="1031" width="1247" height="434" frameX="-3" frameY="-123" frameWidth="1409" frameHeight="654"/>
	<SubTexture name="dadAppear0033" x="5653" y="1031" width="1069" height="490" frameX="-93" frameY="-76" frameWidth="1409" frameHeight="654"/>
	<SubTexture name="dadAppear0034" x="6732" y="1031" width="1155" height="556" frameX="-92" frameY="-38" frameWidth="1409" frameHeight="654"/>
	<SubTexture name="dadAppear0035" x="10" y="1597" width="1020" height="495" frameX="-160" frameY="-118" frameWidth="1409" frameHeight="654"/>
	<SubTexture name="dadAppear0036" x="1040" y="1597" width="1190" height="487" frameX="-89" frameY="-132" frameWidth="1409" frameHeight="654"/>
	<SubTexture name="dadAppear0037" x="2240" y="1597" width="1348" height="478" frameX="-23" frameY="-132" frameWidth="1409" frameHeight="654"/>
	<SubTexture name="dadAppear0038" x="3598" y="1597" width="1404" height="488" frameX="0" frameY="-122" frameWidth="1409" frameHeight="654"/>
	<SubTexture name="dadAppear0039" x="5012" y="1597" width="1179" height="540" frameX="-100" frameY="-71" frameWidth="1409" frameHeight="654"/>
	<SubTexture name="dadAppear0040" x="6201" y="1597" width="1200" height="578" frameX="-94" frameY="-34" frameWidth="1409" frameHeight="654"/>
	<SubTexture name="dadAppear0041" x="10" y="2185" width="1040" height="504" frameX="-162" frameY="-118" frameWidth="1409" frameHeight="654"/>
	<SubTexture name="dadAppear0042" x="1060" y="2185" width="1204" height="492" frameX="-90" frameY="-132" frameWidth="1409" frameHeight="654"/>
	<SubTexture name="dadAppear0043" x="2274" y="2185" width="1356" height="481" frameX="-23" frameY="-132" frameWidth="1409" frameHeight="654"/>
	<SubTexture name="dadAppear0044" x="3640" y="2185" width="1409" height="490" frameX="0" frameY="-122" frameWidth="1409" frameHeight="654"/>
	<SubTexture name="dadAppear0045" x="5059" y="2185" width="1180" height="541" frameX="-100" frameY="-71" frameWidth="1409" frameHeight="654"/>
	<SubTexture name="dadAppear0046" x="6249" y="2185" width="1201" height="578" frameX="-94" frameY="-34" frameWidth="1409" frameHeight="654"/>
	<SubTexture name="dadAppear0047" x="10" y="2773" width="1040" height="504" frameX="-162" frameY="-118" frameWidth="1409" frameHeight="654"/>
	<SubTexture name="dadAppear0048" x="1060" y="2773" width="1204" height="492" frameX="-90" frameY="-132" frameWidth="1409" frameHeight="654"/>
	<SubTexture name="dadAppear0049" x="2274" y="2773" width="1356" height="481" frameX="-23" frameY="-132" frameWidth="1409" frameHeight="654"/>
	<SubTexture name="dadAppear0050" x="3640" y="2773" width="1409" height="490" frameX="0" frameY="-122" frameWidth="1409" frameHeight="654"/>
	<SubTexture name="dadAppear0051" x="5059" y="2773" width="1180" height="541" frameX="-100" frameY="-71" frameWidth="1409" frameHeight="654"/>
	<SubTexture name="dadAppear0052" x="6249" y="2773" width="1201" height="578" frameX="-94" frameY="-34" frameWidth="1409" frameHeight="654"/>
	<SubTexture name="dadAppear0053" x="10" y="3361" width="1040" height="504" frameX="-162" frameY="-118" frameWidth="1409" frameHeight="654"/>
	<SubTexture name="dadAppear0054" x="1060" y="3361" width="1204" height="492" frameX="-90" frameY="-132" frameWidth="1409" frameHeight="654"/>
	<SubTexture name="dadAppear0055" x="2274" y="3361" width="1356" height="481" frameX="-23" frameY="-132" frameWidth="1409" frameHeight="654"/>
	<SubTexture name="dadAppear0056" x="3640" y="3361" width="1409" height="490" frameX="0" frameY="-122" frameWidth="1409" frameHeight="654"/>
	<SubTexture name="dadAppear0057" x="5059" y="3361" width="1180" height="541" frameX="-100" frameY="-71" frameWidth="1409" frameHeight="654"/>
	<SubTexture name="dadAppear0058" x="6249" y="3361" width="1201" height="578" frameX="-94" frameY="-34" frameWidth="1409" frameHeight="654"/>
	<SubTexture name="dadAppear0059" x="10" y="3949" width="1040" height="504" frameX="-162" frameY="-118" frameWidth="1409" frameHeight="654"/>
	<SubTexture name="dadAppear0060" x="1060" y="3949" width="1204" height="492" frameX="-90" frameY="-132" frameWidth="1409" frameHeight="654"/>
	<SubTexture name="dadAppear0061" x="2274" y="3949" width="1356" height="481" frameX="-23" frameY="-132" frameWidth="1409" frameHeight="654"/>
	<SubTexture name="dadAppear0062" x="3640" y="3949" width="1409" height="490" frameX="0" frameY="-122" frameWidth="1409" frameHeight="654"/>
	<SubTexture name="dadAppear0063" x="5059" y="3949" width="1180" height="541" frameX="-100" frameY="-71" frameWidth="1409" frameHeight="654"/>
	<SubTexture name="dadAppear0064" x="6249" y="3949" width="1201" height="578" frameX="-94" frameY="-34" frameWidth="1409" frameHeight="654"/>
</TextureAtlas>
